{"coursesWithCoupon":{"https://www.udemy.com/course/henry-zhang-side-hustle-mastery/":{"courseDetails":{"courseId":3964500,"title":"Side Hustle Mastery 2022","shortDescription":"How to master the 7 Strategies to Start Your Profitable Online Side Hustles and make more while working full time easily","longDescription":null,"language":"English","courseUri":"https://www.udemy.com/course/henry-zhang-side-hustle-mastery/","imageUri":"https://img-c.udemycdn.com/course/750x422/3964500_0a82_3.jpg","duration":"1 total hour","enrolledStudentsCount":"19,637 students","lastUpdated":null,"targetAudiences":["Anyone Who Wants to Make Money Online with Side Hustles","Anyone Who Wants Additional Passive Income Streams","Anyone Who Wants to Fire Their Boss"],"tags":["Business","Entrepreneurship","Online Business"],"rating":{"count":58,"averageValue":"3.5"},"instructors":[{"name":"Henry Zhang","url":"/user/henry-zhang-26/","totalNumberOfStudents":200706,"totalNumberOfReviews":3343,"averageRating":3.936086841116752},{"name":"Henry Zhang Support","url":"/user/henry-zhang-support/","totalNumberOfStudents":200706,"totalNumberOfReviews":3343,"averageRating":3.936086841116752}]},"isAlreadyAFreeCourse":false,"couponData":{"couponCode":"AF20FBCF8D5161CF757F","originalPrice":"\u20B93,399","discountedPrice":"Free","expirationText":"3 days","discountPercentage":100}},"https://www.udemy.com/course/el-arte-de-programar-en-r-anade-valor-a-tu-cv/":{"courseDetails":{"courseId":1999002,"title":"R Studio: Empieza desde cero","shortDescription":"Aprende programaci\u00F3n en R en R Studio. Aprender\u00E1s a usar vectores, matrices, funciones, gr\u00E1ficas, paquetes y m\u00E1s.","longDescription":null,"language":"Spanish","courseUri":"https://www.udemy.com/course/el-arte-de-programar-en-r-anade-valor-a-tu-cv/","imageUri":"https://img-c.udemycdn.com/course/750x422/1999002_c5bf_11.jpg","duration":"1.5 total hours","enrolledStudentsCount":"64,554 students","lastUpdated":null,"targetAudiences":["Este curso es para ti si quieres aprender a programar en R.","Cualquier persona interesada en la programaci\u00F3n estad\u00EDstica.","Cualquier persona interesada en convertirse en un cient\u00EDfico de datos."],"tags":["Development","Programming Languages","R (programming language)"],"rating":{"count":1097,"averageValue":"4.4"},"instructors":[{"name":"Ra\u00FAl Montesinos","url":"/user/ralmontesinos/","totalNumberOfStudents":349839,"totalNumberOfReviews":11787,"averageRating":4.3623648394262045},{"name":"Numpi Cursos","url":"/user/numpi/","totalNumberOfStudents":340365,"totalNumberOfReviews":26161,"averageRating":4.369865950227754}]},"isAlreadyAFreeCourse":false,"couponData":{"couponCode":"37E6E208687E98024534","originalPrice":"\u20B9799","discountedPrice":"Free","expirationText":"4 days","discountPercentage":100}},"https://www.udemy.com/course/microsoft-excel-intermedio/":{"courseDetails":{"courseId":3593486,"title":"Microsoft Excel: Intermedio, Funciones, Tablas Din\u00E1micas y \u002B","shortDescription":"Aumenta tu productividad y amplia tus herramientas de an\u00E1lisis","longDescription":null,"language":"Spanish","courseUri":"https://www.udemy.com/course/microsoft-excel-intermedio/","imageUri":"https://img-c.udemycdn.com/course/750x422/3593486_2487_17.jpg","duration":"2 total hours","enrolledStudentsCount":"68,313 students","lastUpdated":null,"targetAudiences":["Profesionales que quieran dominar excel.","Profesionales que quieran realizar sus tareas m\u00E1s eficientemente.","Profesionales que necesiten el manejo de Excel para cuestiones laborales."],"tags":["Office Productivity","Microsoft","Excel"],"rating":{"count":1527,"averageValue":"4.4"},"instructors":[{"name":"Numpi Cursos","url":"/user/numpi/","totalNumberOfStudents":340365,"totalNumberOfReviews":26161,"averageRating":4.369865950227754}]},"isAlreadyAFreeCourse":false,"couponData":{"couponCode":"C0BA29140EEF68D4C306","originalPrice":"\u20B93,899","discountedPrice":"Free","expirationText":"4 days","discountPercentage":100}},"https://www.udemy.com/course/el-curso-completo-de-google-sheets-desde-cero/":{"courseDetails":{"courseId":3694482,"title":"Google Spreadsheets: Empieza desde cero","shortDescription":"La mejor alternativa a Microsoft Excel. Domina las hojas de c\u00E1lculo de Google.","longDescription":null,"language":"Spanish","courseUri":"https://www.udemy.com/course/el-curso-completo-de-google-sheets-desde-cero/","imageUri":"https://img-c.udemycdn.com/course/750x422/3694482_eed8_14.jpg","duration":"1.5 total hours","enrolledStudentsCount":"51,851 students","lastUpdated":null,"targetAudiences":["Estudiantes, profesionistas y emprendedores que quieran aprender a usar herramientas en la nube.","Estudiantes, profesionistas y emprendedores que requieran una herramienta para trabajar con datos de forma gratuita.","Estudiantes, profesionistas y emprendedores que quieran aprender a trabajar con datos con herramientas en la nube."],"tags":["Office Productivity","Google","Google Sheets"],"rating":{"count":531,"averageValue":"4.4"},"instructors":[{"name":"Ra\u00FAl Montesinos","url":"/user/ralmontesinos/","totalNumberOfStudents":349839,"totalNumberOfReviews":11787,"averageRating":4.3623648394262045},{"name":"Numpi Cursos","url":"/user/numpi/","totalNumberOfStudents":340365,"totalNumberOfReviews":26161,"averageRating":4.369865950227754}]},"isAlreadyAFreeCourse":false,"couponData":{"couponCode":"6D15C223277FEAA87AA1","originalPrice":"\u20B9799","discountedPrice":"Free","expirationText":"4 days","discountPercentage":100}},"https://www.udemy.com/course/r-desde-cero-el-curso-mas-poderoso/":{"courseDetails":{"courseId":4059254,"title":"R Programming: Aprende a programar en R desde cero","shortDescription":"Vu\u00E9lvete un experto del an\u00E1lisis de datos con R.","longDescription":null,"language":"Spanish","courseUri":"https://www.udemy.com/course/r-desde-cero-el-curso-mas-poderoso/","imageUri":"https://img-c.udemycdn.com/course/750x422/4059254_1644_22.jpg","duration":"6.5 total hours","enrolledStudentsCount":"60,054 students","lastUpdated":null,"targetAudiences":["Profesionistas que quieran aprender a analizar datos en R.","Estudiantes que quieran aprender a analizar datos en R.","Profesionistas que quieran aprender a realizar gr\u00E1ficos super vendedores con R.","Estudiantes y profesionales que quieran entrar en el mundo del an\u00E1lisis de datos con R."],"tags":["Development","Programming Languages","R (programming language)"],"rating":{"count":639,"averageValue":"4.4"},"instructors":[{"name":"Numpi Cursos","url":"/user/numpi/","totalNumberOfStudents":340365,"totalNumberOfReviews":26161,"averageRating":4.369865950227754}]},"isAlreadyAFreeCourse":false,"couponData":{"couponCode":"A6EBE3AD45712A1DEEB1","originalPrice":"\u20B93,899","discountedPrice":"Free","expirationText":"4 days","discountPercentage":100}},"https://www.udemy.com/course/data-analysis-con-sql-y-tableau/":{"courseDetails":{"courseId":4025408,"title":"Microsoft SQL Server: An\u00E1lisis de datos con Tableau","shortDescription":"Mejora tus habilidades anal\u00EDticas comerciales con SQL y visualizaci\u00F3n de datos","longDescription":null,"language":"Spanish","courseUri":"https://www.udemy.com/course/data-analysis-con-sql-y-tableau/","imageUri":"https://img-c.udemycdn.com/course/750x422/4025408_2095_14.jpg","duration":"2 total hours","enrolledStudentsCount":"60,900 students","lastUpdated":null,"targetAudiences":["Estudiantes y profesionales que quieran entrar en el mundo de los datos y el Business Intelligence."],"tags":["Business","Business Analytics \u0026 Intelligence","Data Analysis"],"rating":{"count":482,"averageValue":"4.6"},"instructors":[{"name":"Numpi Cursos","url":"/user/numpi/","totalNumberOfStudents":340365,"totalNumberOfReviews":26161,"averageRating":4.369865950227754},{"name":"Ra\u00FAl Montesinos","url":"/user/ralmontesinos/","totalNumberOfStudents":349839,"totalNumberOfReviews":11787,"averageRating":4.3623648394262045}]},"isAlreadyAFreeCourse":false,"couponData":{"couponCode":"E3EE94ED81216986909F","originalPrice":"\u20B93,899","discountedPrice":"Free","expirationText":"4 days","discountPercentage":100}},"https://www.udemy.com/course/power-bi-2021-proyectos-reales-para-volverte-un-master/":{"courseDetails":{"courseId":4004864,"title":"Power BI: 8 Proyectos reales para volverte un master","shortDescription":"Vu\u00E9lvete un experto del Business Intelligence y extrae valor de los datos","longDescription":null,"language":"Spanish","courseUri":"https://www.udemy.com/course/power-bi-2021-proyectos-reales-para-volverte-un-master/","imageUri":"https://img-c.udemycdn.com/course/750x422/4004864_c2d2_18.jpg","duration":"4 total hours","enrolledStudentsCount":"59,264 students","lastUpdated":null,"targetAudiences":["Estudiantes y profesionales que quieran entrar en el mundo de los datos y el Business Intelligence.","Estudiantes y profesionales que quieran aprender a utilizar Power BI."],"tags":["Business","Business Analytics \u0026 Intelligence","Microsoft Power BI"],"rating":{"count":627,"averageValue":"4.4"},"instructors":[{"name":"Numpi Cursos","url":"/user/numpi/","totalNumberOfStudents":340365,"totalNumberOfReviews":26161,"averageRating":4.369865950227754}]},"isAlreadyAFreeCourse":false,"couponData":{"couponCode":"F0896F0D31F32204F866","originalPrice":"\u20B93,899","discountedPrice":"Free","expirationText":"4 days","discountPercentage":100}},"https://www.udemy.com/course/power-bi-dax-avanzado/":{"courseDetails":{"courseId":4183410,"title":"Power BI DAX: Aprende las funciones m\u00E1s avanzadas","shortDescription":"Vu\u00E9lvete un profesional de Power BI y del Business Intelligence","longDescription":null,"language":"Spanish","courseUri":"https://www.udemy.com/course/power-bi-dax-avanzado/","imageUri":"https://img-c.udemycdn.com/course/750x422/4183410_f7ca_14.jpg","duration":"9 total hours","enrolledStudentsCount":"38,903 students","lastUpdated":null,"targetAudiences":["Estudiantes y profesionales que quieran brillar en el mundo de los datos y el Business Intelligence.","Estudiantes y profesionales que quieran aprender a utilizar Power BI avanzado."],"tags":["Office Productivity","Microsoft","DAX"],"rating":{"count":439,"averageValue":"4.2"},"instructors":[{"name":"Numpi Cursos","url":"/user/numpi/","totalNumberOfStudents":340365,"totalNumberOfReviews":26161,"averageRating":4.369865950227754}]},"isAlreadyAFreeCourse":false,"couponData":{"couponCode":"FF2490092436B5D62D8C","originalPrice":"\u20B93,899","discountedPrice":"Free","expirationText":"4 days","discountPercentage":100}},"https://www.udemy.com/course/power-bi-desde-cero/":{"courseDetails":{"courseId":3944270,"title":"Power BI: Empieza desde cero","shortDescription":"Aprende con Power BI a darle valor a los datos","longDescription":null,"language":"Spanish","courseUri":"https://www.udemy.com/course/power-bi-desde-cero/","imageUri":"https://img-c.udemycdn.com/course/750x422/3944270_2fe3_19.jpg","duration":"6 total hours","enrolledStudentsCount":"73,143 students","lastUpdated":null,"targetAudiences":["Estudiantes y profesionales que quieran entrar en el mundo de los datos y el Business Intelligence.","Estudiantes y profesionales que quieran aprender a utilizar Power BI."],"tags":["Business","Business Analytics \u0026 Intelligence","Microsoft Power BI"],"rating":{"count":1731,"averageValue":"4.2"},"instructors":[{"name":"Numpi Cursos","url":"/user/numpi/","totalNumberOfStudents":340365,"totalNumberOfReviews":26161,"averageRating":4.369865950227754}]},"isAlreadyAFreeCourse":false,"couponData":{"couponCode":"C41860D2B5FA502F809F","originalPrice":"\u20B93,899","discountedPrice":"Free","expirationText":"4 days","discountPercentage":100}},"https://www.udemy.com/course/microsoft-excel-analisis-de-datos-con-tablas-dinamicas/":{"courseDetails":{"courseId":2695676,"title":"Microsoft Excel: An\u00E1lisis de datos con tablas din\u00E1micas","shortDescription":"La herramienta m\u00E1s poderosa de Excel.","longDescription":null,"language":"Spanish","courseUri":"https://www.udemy.com/course/microsoft-excel-analisis-de-datos-con-tablas-dinamicas/","imageUri":"https://img-c.udemycdn.com/course/750x422/2695676_712d_14.jpg","duration":"1 total hour","enrolledStudentsCount":"73,793 students","lastUpdated":null,"targetAudiences":["Usuarios de Excel que quieran conocer y dominar la herramienta m\u00E1s potente que tiene Excel para analizar datos."],"tags":["Office Productivity","Microsoft","Pivot Tables"],"rating":{"count":1930,"averageValue":"4.4"},"instructors":[{"name":"Ra\u00FAl Montesinos","url":"/user/ralmontesinos/","totalNumberOfStudents":349839,"totalNumberOfReviews":11787,"averageRating":4.3623648394262045},{"name":"Numpi Cursos","url":"/user/numpi/","totalNumberOfStudents":340365,"totalNumberOfReviews":26161,"averageRating":4.369865950227754}]},"isAlreadyAFreeCourse":false,"couponData":{"couponCode":"D57B9FC6963940A6ECC6","originalPrice":"\u20B9799","discountedPrice":"Free","expirationText":"4 days","discountPercentage":100}},"https://www.udemy.com/course/tableau-10-desde-cero/":{"courseDetails":{"courseId":2288849,"title":"Tableau: Empieza desde cero","shortDescription":"Entra al mundo del business intelligence y aprende a visualizar grandes cantidades de informaci\u00F3n.","longDescription":null,"language":"Spanish","courseUri":"https://www.udemy.com/course/tableau-10-desde-cero/","imageUri":"https://img-c.udemycdn.com/course/750x422/2288849_5725_9.jpg","duration":"1.5 total hours","enrolledStudentsCount":"51,232 students","lastUpdated":null,"targetAudiences":["Deber\u00EDa tomar este curso si desea aprender Tableau completamente desde cero.","Deber\u00EDas tomar este curso si conoces algunas habilidades de Tableau pero quieres mejorar.","Debe tomar este curso si es bueno con Tableau y desea llevar sus habilidades al siguiente nivel y realmente aprovechar todo el potencial de Tableau."],"tags":["Business","Business Analytics \u0026 Intelligence","Tableau"],"rating":{"count":545,"averageValue":"4.2"},"instructors":[{"name":"Ra\u00FAl Montesinos","url":"/user/ralmontesinos/","totalNumberOfStudents":349839,"totalNumberOfReviews":11787,"averageRating":4.3623648394262045},{"name":"Numpi Cursos","url":"/user/numpi/","totalNumberOfStudents":340365,"totalNumberOfReviews":26161,"averageRating":4.369865950227754}]},"isAlreadyAFreeCourse":false,"couponData":{"couponCode":"5EB7AC2147C5E98921B7","originalPrice":"\u20B9799","discountedPrice":"Free","expirationText":"4 days","discountPercentage":100}},"https://www.udemy.com/course/aprende-sql-desde-cero-curso-con-mas-de-50-ejercicios/":{"courseDetails":{"courseId":2040612,"title":"Aprende SQL desde cero: \u00A1Curso con mas de 50 ejercicios! 1","shortDescription":"Un curso integral donde aprender\u00E1s como hacer consultas SQL complejas.","longDescription":null,"language":"Spanish","courseUri":"https://www.udemy.com/course/aprende-sql-desde-cero-curso-con-mas-de-50-ejercicios/","imageUri":"https://img-c.udemycdn.com/course/750x422/2040612_6147_12.jpg","duration":"1.5 total hours","enrolledStudentsCount":"80,820 students","lastUpdated":null,"targetAudiences":["Cualquier persona interesada en aprender m\u00E1s sobre SQL o an\u00E1lisis de datos."],"tags":["Development","Database Design \u0026 Development","SQL"],"rating":{"count":2339,"averageValue":"4.5"},"instructors":[{"name":"Ra\u00FAl Montesinos","url":"/user/ralmontesinos/","totalNumberOfStudents":349839,"totalNumberOfReviews":11787,"averageRating":4.3623648394262045},{"name":"Numpi Cursos","url":"/user/numpi/","totalNumberOfStudents":340365,"totalNumberOfReviews":26161,"averageRating":4.369865950227754}]},"isAlreadyAFreeCourse":false,"couponData":{"couponCode":"8901120624A881F5EE18","originalPrice":"\u20B9799","discountedPrice":"Free","expirationText":"4 days","discountPercentage":100}},"https://www.udemy.com/course/henry-zhang-public-speaking-mini-course/":{"courseDetails":{"courseId":4062702,"title":"Public Speaking Mastery 2022","shortDescription":"How to become more confident when speaking in public to establish your personal brand \u0026 influence people  successfully !","longDescription":null,"language":"English","courseUri":"https://www.udemy.com/course/henry-zhang-public-speaking-mini-course/","imageUri":"https://img-c.udemycdn.com/course/750x422/4062702_ca7f_5.jpg","duration":"1 total hour","enrolledStudentsCount":"19,084 students","lastUpdated":null,"targetAudiences":["Anyone Who Wants to Make Money Online with Public Speaking","Anyone Who Wants Additional Passive Income Streams","Anyone Who Wants to Fire Their Boss"],"tags":["Personal Development","Influence","Public Speaking"],"rating":{"count":100,"averageValue":"4.4"},"instructors":[{"name":"Henry Zhang","url":"/user/henry-zhang-26/","totalNumberOfStudents":200706,"totalNumberOfReviews":3343,"averageRating":3.936086841116752},{"name":"Henry Zhang Support","url":"/user/henry-zhang-support/","totalNumberOfStudents":200706,"totalNumberOfReviews":3343,"averageRating":3.936086841116752}]},"isAlreadyAFreeCourse":false,"couponData":{"couponCode":"99237CBD3EF8E1A02782","originalPrice":"\u20B93,399","discountedPrice":"Free","expirationText":"3 days","discountPercentage":100}},"https://www.udemy.com/course/henry-zhang-amazon-fba-mini-course/":{"courseDetails":{"courseId":4093762,"title":"Amazon FBA Mastery 2022","shortDescription":"How to make big profits on Amazon without a lot of upfront investment and worrying abt logistics and customer services !","longDescription":null,"language":"English","courseUri":"https://www.udemy.com/course/henry-zhang-amazon-fba-mini-course/","imageUri":"https://img-c.udemycdn.com/course/750x422/4093762_a0d1_7.jpg","duration":"34 total mins","enrolledStudentsCount":"19,327 students","lastUpdated":null,"targetAudiences":["Anyone Who Wants to Scale their Success by Amazon FBA","Anyone Who Wants Additional Passive Income Streams","Anyone Who Wants to Fire Their Boss"],"tags":["Business","E-Commerce","Amazon FBA"],"rating":{"count":173,"averageValue":"4.1"},"instructors":[{"name":"Henry Zhang","url":"/user/henry-zhang-26/","totalNumberOfStudents":200706,"totalNumberOfReviews":3343,"averageRating":3.936086841116752},{"name":"Henry Zhang Support","url":"/user/henry-zhang-support/","totalNumberOfStudents":200706,"totalNumberOfReviews":3343,"averageRating":3.936086841116752}]},"isAlreadyAFreeCourse":false,"couponData":{"couponCode":"4021EDD01D45F5883DB1","originalPrice":"\u20B93,399","discountedPrice":"Free","expirationText":"3 days","discountPercentage":100}},"https://www.udemy.com/course/como-crear-una-tienda-online-con-wordpress-desde-cero/":{"courseDetails":{"courseId":4556704,"title":"C\u00F3mo Crear una Tienda Online con WordPress Desde Cero 2022","shortDescription":"Aprende a c\u00F3mo crear una tienda online con WordPress para vender tus productos por Internet de forma f\u00E1cil y simple.","longDescription":null,"language":"Spanish","courseUri":"https://www.udemy.com/course/como-crear-una-tienda-online-con-wordpress-desde-cero/","imageUri":"https://img-c.udemycdn.com/course/750x422/4556704_fc04.jpg","duration":"1.5 total hours","enrolledStudentsCount":"12,025 students","lastUpdated":null,"targetAudiences":["Personas Interesadas en crear su propia tienda online de forma profesional.","Personas que no sepan programar pero que quieran crear una tienda online profesional.","Emprendedores y personas que quieran vender por internet.","Empresas y Startups que quieran aumentar las ventas de sus productos creando una tienda online.","Personas que quieran aprender a usar WordPress de forma profesional."],"tags":["Design","Web Design","WooCommerce"],"rating":{"count":83,"averageValue":"4.4"},"instructors":[{"name":"Renato Jes\u00FAs Yacolca Neyra","url":"/user/renato-jesus-yacolca-neyra-2/","totalNumberOfStudents":88055,"totalNumberOfReviews":1989,"averageRating":4.222304349557523}]},"isAlreadyAFreeCourse":false,"couponData":{"couponCode":"TIENDA-GR14","originalPrice":"\u20B97,900","discountedPrice":"Free","expirationText":"4 days","discountPercentage":100}},"https://www.udemy.com/course/comptia-a-core2-220-1002/":{"courseDetails":{"courseId":3500082,"title":"A\u002B Core2 Practice Test","shortDescription":"500 Questions with Accurate Answers","longDescription":null,"language":"English","courseUri":"https://www.udemy.com/course/comptia-a-core2-220-1002/","imageUri":"https://img-c.udemycdn.com/course/750x422/3500082_c600.jpg","duration":"500 questions","enrolledStudentsCount":"9,219 students","lastUpdated":null,"targetAudiences":["Service Desk Analyst","Data Support Technician","Help Desk Tech","Desktop Support Administrator","Technical Support Specialist","End User Computing Technician","Field Service Technician","Help Desk Technician","Associate Network Engineer","System Support Specialist"],"tags":["IT \u0026 Software","IT Certifications","CompTIA A\u002B"],"rating":{"count":19,"averageValue":"4.5"},"instructors":[{"name":"OZ Education","url":"/user/oz-education/","totalNumberOfStudents":96787,"totalNumberOfReviews":296,"averageRating":4.416726071428571}]},"isAlreadyAFreeCourse":false,"couponData":{"couponCode":"C740AFF8C3B77106B0FC","originalPrice":"\u20B9799","discountedPrice":"Free","expirationText":"4 days","discountPercentage":100}},"https://www.udemy.com/course/henry-zhang-influencer-mini-course/":{"courseDetails":{"courseId":4062678,"title":"Social Media Influencer Mastery 2022  | 8-Figure Blueprint !","shortDescription":"How to  Become A Successful Social Media Influencer that Attracts Large Followers and Brands to Beg You For A Promotion!","longDescription":null,"language":"English","courseUri":"https://www.udemy.com/course/henry-zhang-influencer-mini-course/","imageUri":"https://img-c.udemycdn.com/course/750x422/4062678_0a50_2.jpg","duration":"2 total hours","enrolledStudentsCount":"19,689 students","lastUpdated":null,"targetAudiences":["Anyone Who Wants to Scale their Success by Influencer Marketing","Anyone Who Wants Additional Passive Income Streams","Anyone Who Wants to Fire Their Boss"],"tags":["Marketing","Social Media Marketing","Influencer Marketing"],"rating":{"count":71,"averageValue":"4.1"},"instructors":[{"name":"Henry Zhang","url":"/user/henry-zhang-26/","totalNumberOfStudents":200706,"totalNumberOfReviews":3343,"averageRating":3.936086841116752},{"name":"Henry Zhang Support","url":"/user/henry-zhang-support/","totalNumberOfStudents":200706,"totalNumberOfReviews":3343,"averageRating":3.936086841116752}]},"isAlreadyAFreeCourse":false,"couponData":{"couponCode":"183F1D3BEDD543AA9A72","originalPrice":"\u20B94,299","discountedPrice":"Free","expirationText":"3 days","discountPercentage":100}},"https://www.udemy.com/course/aws-certified-solutions-architect-associate-practice-exams-new/":{"courseDetails":{"courseId":4686764,"title":"AWS Certified Solutions Architect Associate Practice Exams","shortDescription":"Prepare for AWS Solutions Architect | AWS Certified Solutions Architect Associate [SAA-C02] Practice Tests 2022","longDescription":null,"language":"English","courseUri":"https://www.udemy.com/course/aws-certified-solutions-architect-associate-practice-exams-new/","imageUri":"https://img-b.udemycdn.com/course/750x422/4686764_0887_5.jpg","duration":"60 questions","enrolledStudentsCount":"3,069 students","lastUpdated":null,"targetAudiences":["Anyone, who is preparing for the AWS Certified Solutions Architect - Associate exam SAA-C02","All IT Professionals who want to boost AWS knowledge for AWS Job interview","Students who want to test their knowledge for exams"],"tags":["IT \u0026 Software","IT Certifications","AWS Certification"],"rating":{"count":9,"averageValue":"4.3"},"instructors":[{"name":"Odoben Academy","url":"/user/odoben/","totalNumberOfStudents":12939,"totalNumberOfReviews":78,"averageRating":4.633989246153846}]},"isAlreadyAFreeCourse":false,"couponData":{"couponCode":"820BF85CEF17DD289548","originalPrice":"\u20B9799","discountedPrice":"Free","expirationText":"4 days","discountPercentage":100}},"https://www.udemy.com/course/aws-certified-solutions-architect-associate-practice-exam-jv/":{"courseDetails":{"courseId":3810896,"title":"Certified Solutions Architect \u2013 Associate Practice Test","shortDescription":"500 Questions with Accurate Answers","longDescription":null,"language":"English","courseUri":"https://www.udemy.com/course/aws-certified-solutions-architect-associate-practice-exam-jv/","imageUri":"https://img-c.udemycdn.com/course/750x422/3810896_74ac_2.jpg","duration":"500 questions","enrolledStudentsCount":"19,420 students","lastUpdated":null,"targetAudiences":["Students who want to take AWS Certified Solutions Architect \u2013 Associate Certificae"],"tags":["IT \u0026 Software","IT Certifications","AWS Certification"],"rating":{"count":27,"averageValue":"4.8"},"instructors":[{"name":"OZ Education","url":"/user/oz-education/","totalNumberOfStudents":96787,"totalNumberOfReviews":296,"averageRating":4.416726071428571}]},"isAlreadyAFreeCourse":false,"couponData":{"couponCode":"8DE9CF26D0B2DEA25917","originalPrice":"\u20B9799","discountedPrice":"Free","expirationText":"4 days","discountPercentage":100}},"https://www.udemy.com/course/fun-and-effective-learning/":{"courseDetails":{"courseId":4479772,"title":"Stress-free Effective Learning for Adults: Crush your goals!","shortDescription":"Become a superlearner! - Complete practical training in learning:  Avoid procrastination, and increase productivity","longDescription":null,"language":"English","courseUri":"https://www.udemy.com/course/fun-and-effective-learning/","imageUri":"https://img-c.udemycdn.com/course/750x422/4479772_5c1a_3.jpg","duration":"1.5 total hours","enrolledStudentsCount":"7,584 students","lastUpdated":null,"targetAudiences":["This course is for anybody who wants to become a superlearner and break-through in any subject.","It is targeted mainly to two publics. On one side, students willing to improve their marks. On the other side, to working people who want to advance in their careers."],"tags":["Personal Development","Stress Management"],"rating":{"count":39,"averageValue":"4.4"},"instructors":[{"name":"Dr. Marcel Tella Amo","url":"/user/marcel-tella/","totalNumberOfStudents":7584,"totalNumberOfReviews":39,"averageRating":4.3864484}]},"isAlreadyAFreeCourse":false,"couponData":{"couponCode":"19B436714DE154107557","originalPrice":"\u20B9999","discountedPrice":"Free","expirationText":"3 days","discountPercentage":100}},"https://www.udemy.com/course/basic-portrait-sketching-techniques-for-beginners/":{"courseDetails":{"courseId":3969404,"title":"Basic Portrait Drawing Techniques- Beginners and Advanced","shortDescription":"Realistic human portrait Drawing,Shading technique with pencil powder, Pencil drawing, Step-by-step portrait sketching","longDescription":null,"language":"English","courseUri":"https://www.udemy.com/course/basic-portrait-sketching-techniques-for-beginners/","imageUri":"https://img-c.udemycdn.com/course/750x422/3969404_a706_2.jpg","duration":"3.5 total hours","enrolledStudentsCount":"3,123 students","lastUpdated":null,"targetAudiences":["All painting students, especially beginners","And all students who are interested in sketching and creating a portrait"],"tags":["Lifestyle","Arts \u0026 Crafts","Portraiture"],"rating":{"count":3,"averageValue":"4.4"},"instructors":[{"name":"Mariya Karim","url":"/user/mariya-karim/","totalNumberOfStudents":5160,"totalNumberOfReviews":141,"averageRating":4.472982763043477},{"name":"Milad Ahmadi","url":"/user/e9a261b7-66f2-448d-b8d8-3d1a77cb4301/","totalNumberOfStudents":82419,"totalNumberOfReviews":3712,"averageRating":4.220319130917874}]},"isAlreadyAFreeCourse":false,"couponData":{"couponCode":"FREEDRAW11JUN","originalPrice":"\u20B93,699","discountedPrice":"Free","expirationText":"4 days","discountPercentage":100}},"https://www.udemy.com/course/the-complete-business-interview-course/":{"courseDetails":{"courseId":4583066,"title":"The Complete Business Interview Course","shortDescription":"Prepare for the Most Common Interview Questions as well as answering techniques.","longDescription":null,"language":"English","courseUri":"https://www.udemy.com/course/the-complete-business-interview-course/","imageUri":"https://img-c.udemycdn.com/course/750x422/4583066_6d68_2.jpg","duration":"3 total hours","enrolledStudentsCount":"3,149 students","lastUpdated":null,"targetAudiences":["Anyone who wants to have a job or plans to have some interviews"],"tags":["Personal Development","Career Development","Interviewing Skills"],"rating":{"count":18,"averageValue":"4.9"},"instructors":[{"name":"World English Academy","url":"/user/world-english-academy/","totalNumberOfStudents":8313,"totalNumberOfReviews":82,"averageRating":4.513649285294117}]},"isAlreadyAFreeCourse":false,"couponData":{"couponCode":"F9C063FF9C1B8B6CEBC7","originalPrice":"\u20B9799","discountedPrice":"Free","expirationText":"4 days","discountPercentage":100}},"https://www.udemy.com/course/henry-zhang-nft-mini-course/":{"courseDetails":{"courseId":4140508,"title":"NFT Mastery 2022","shortDescription":"Learn everything you need to know about NFTs and How You Can Get Started Today","longDescription":null,"language":"English","courseUri":"https://www.udemy.com/course/henry-zhang-nft-mini-course/","imageUri":"https://img-c.udemycdn.com/course/750x422/4140508_9a3b_3.jpg","duration":"39 total mins","enrolledStudentsCount":"4,136 students","lastUpdated":null,"targetAudiences":["Anyone Who Wants to Scale their Success by NFT","Anyone Who Wants Additional Passive Income Streams","Anyone Who Wants to Fire Their Boss"],"tags":["Finance \u0026 Accounting","Cryptocurrency \u0026 Blockchain","NFT (Non-Fungible Tokens)"],"rating":{"count":10,"averageValue":"3.6"},"instructors":[{"name":"Henry Zhang","url":"/user/henry-zhang-26/","totalNumberOfStudents":200706,"totalNumberOfReviews":3343,"averageRating":3.936086841116752},{"name":"Henry Zhang Support","url":"/user/henry-zhang-support/","totalNumberOfStudents":200706,"totalNumberOfReviews":3343,"averageRating":3.936086841116752}]},"isAlreadyAFreeCourse":false,"couponData":{"couponCode":"9160A75FB26D5614A08F","originalPrice":"\u20B93,299","discountedPrice":"Free","expirationText":"3 days","discountPercentage":100}},"https://www.udemy.com/course/introduction-to-quantum-computing/":{"courseDetails":{"courseId":3473250,"title":"Introduction to Quantum Computing","shortDescription":"Master Quantum Computing and Understand all the Basics of Quantum Computing in just one course","longDescription":null,"language":"English","courseUri":"https://www.udemy.com/course/introduction-to-quantum-computing/","imageUri":"https://img-c.udemycdn.com/course/750x422/3473250_4782_2.jpg","duration":"2.5 total hours","enrolledStudentsCount":"94,932 students","lastUpdated":null,"targetAudiences":["People interested by Quantum Computing","People curious about learning a new topic"],"tags":["Development","Software Engineering","Quantum Computing"],"rating":{"count":472,"averageValue":"3.7"},"instructors":[{"name":"Yassin Marco","url":"/user/ataouyl-yassin/","totalNumberOfStudents":1159515,"totalNumberOfReviews":40591,"averageRating":4.2300512665277195}]},"isAlreadyAFreeCourse":false,"couponData":{"couponCode":"7E9F8B5E9E93866014A6","originalPrice":"\u20B91,299","discountedPrice":"Free","expirationText":"4 days","discountPercentage":100}},"https://www.udemy.com/course/microsoft-excel-basic-excel-advanced-excel-formulas/":{"courseDetails":{"courseId":3338560,"title":"Microsoft Excel -Basic Excel/ Advanced Excel Formulas","shortDescription":"Learn more than 80\u002B Excel function/Excel formulas/Excel tips for Excel 2007 to Excel 2019 with Excel examples","longDescription":null,"language":"English","courseUri":"https://www.udemy.com/course/microsoft-excel-basic-excel-advanced-excel-formulas/","imageUri":"https://img-c.udemycdn.com/course/750x422/3338560_f31f.jpg","duration":"4.5 total hours","enrolledStudentsCount":"177,408 students","lastUpdated":null,"targetAudiences":["Anyone interested in learning microsoft Excel","Everyone who want to improve there Excel skills"],"tags":["Office Productivity","Microsoft","Excel"],"rating":{"count":3132,"averageValue":"4.3"},"instructors":[{"name":"Yassin Marco","url":"/user/ataouyl-yassin/","totalNumberOfStudents":1159515,"totalNumberOfReviews":40591,"averageRating":4.2300512665277195}]},"isAlreadyAFreeCourse":false,"couponData":{"couponCode":"E59EEF04D69671079910","originalPrice":"\u20B92,999","discountedPrice":"Free","expirationText":"4 days","discountPercentage":100}},"https://www.udemy.com/course/interactive-photography-basics/":{"courseDetails":{"courseId":1644218,"title":"Complete Photography : 21 Courses in 1 [Beginner to Expert]","shortDescription":"Learn Portrait Photography, Landscape Photography, Stock Photography, Photography Composition, Black and White, and more","longDescription":null,"language":"English","courseUri":"https://www.udemy.com/course/interactive-photography-basics/","imageUri":"https://img-b.udemycdn.com/course/750x422/1644218_1b3a.jpg","duration":"8.5 total hours","enrolledStudentsCount":"181,396 students","lastUpdated":null,"targetAudiences":["Who wanna learn Important Photography Basics","Who wanna learn about Exposure Triangle, Histograms, Light Metering and More.","Who wanna expert in Photo Editing, Adobe Lightroom, Adobe Photoshop","Who wanna earn money through photography","Who wanna learn Macro Photography, Black and white photography","Who wanna Earn Passive Income using Photography"],"tags":["Photography \u0026 Video","Photography"],"rating":{"count":2555,"averageValue":"4.5"},"instructors":[{"name":"Creative Online School","url":"/user/mahbubur-rahman-9/","totalNumberOfStudents":1266403,"totalNumberOfReviews":30563,"averageRating":4.269332719402985}]},"isAlreadyAFreeCourse":false,"couponData":{"couponCode":"PHOTO21JUNE2022","originalPrice":"\u20B97,900","discountedPrice":"Free","expirationText":"4 days","discountPercentage":100}},"https://www.udemy.com/course/facebook-ads-2021/":{"courseDetails":{"courseId":2844664,"title":"Best of Facebook Ads: Facebook Ads 2022 Ultimate Pro Edition","shortDescription":"Be a Facebook Ads Consultant - Profit with Facebook Ads: 2022\u0027s Most Powerful Fast Learn Facebook \u0026 Instagram Ads Course","longDescription":null,"language":"English","courseUri":"https://www.udemy.com/course/facebook-ads-2021/","imageUri":"https://img-c.udemycdn.com/course/750x422/2844664_a273_16.jpg","duration":"29.5 total hours","enrolledStudentsCount":"83,987 students","lastUpdated":null,"targetAudiences":["Anyone interested in upskilling and gaining highly in demand digital skills, Facebook junior marketers, Facebook Ads junior Consultants, B2B, B2C, entrepreneurs, start-ups, junior digital marketers, influencers, junior advertisers, job seekers, local businesses, e-commerce businesses \u0026 bloggers."],"tags":["Marketing","Paid Advertising","Facebook Ads"],"rating":{"count":916,"averageValue":"4.4"},"instructors":[{"name":"Ing. Tomas Moravek | Facebook Ads Expert","url":"/user/ing-tomas-moravek-2/","totalNumberOfStudents":666995,"totalNumberOfReviews":16933,"averageRating":4.460993856921085},{"name":"SEO, Facebook Ads \u0026 Digital Marketing Academy","url":"/user/seo-facebook-ads-digital-marketing-academy/","totalNumberOfStudents":666745,"totalNumberOfReviews":16933,"averageRating":4.460993856921085},{"name":"Beck Robertson","url":"/user/beck-robertson-3/","totalNumberOfStudents":603161,"totalNumberOfReviews":14492,"averageRating":4.468198737729815}]},"isAlreadyAFreeCourse":false,"couponData":{"couponCode":"WATERTIGER8","originalPrice":"\u20B97,900","discountedPrice":"Free","expirationText":"4 days","discountPercentage":100}},"https://www.udemy.com/course/hz-time-management-mini-course/":{"courseDetails":{"courseId":3759122,"title":"Time Management Mastery 2022","shortDescription":"How to value your time, make informed decisions about the kind of work you\u2019re focused on and ultimately, beat the clock!","longDescription":null,"language":"English","courseUri":"https://www.udemy.com/course/hz-time-management-mini-course/","imageUri":"https://img-c.udemycdn.com/course/750x422/3759122_33da_3.jpg","duration":"1 total hour","enrolledStudentsCount":"19,543 students","lastUpdated":null,"targetAudiences":["Anyone Who Wants to Make Money Online with Time Management","Anyone Who Wants Additional Passive Income Streams","Anyone Who Wants to Fire Their Boss"],"tags":["Personal Development","Personal Productivity","Time Management"],"rating":{"count":135,"averageValue":"3.4"},"instructors":[{"name":"Henry Zhang","url":"/user/henry-zhang-26/","totalNumberOfStudents":200706,"totalNumberOfReviews":3343,"averageRating":3.936086841116752},{"name":"Henry Zhang Support","url":"/user/henry-zhang-support/","totalNumberOfStudents":200706,"totalNumberOfReviews":3343,"averageRating":3.936086841116752}]},"isAlreadyAFreeCourse":false,"couponData":{"couponCode":"C548EBF847C6D5E2889B","originalPrice":"\u20B93,299","discountedPrice":"Free","expirationText":"3 days","discountPercentage":100}},"https://www.udemy.com/course/for-ukraine/":{"courseDetails":{"courseId":4605168,"title":"For Ukraine","shortDescription":"About Ukraine...for Ukraine","longDescription":null,"language":"English","courseUri":"https://www.udemy.com/course/for-ukraine/","imageUri":"https://img-c.udemycdn.com/course/750x422/4605168_7455.jpg","duration":"2 total hours","enrolledStudentsCount":"696 students","lastUpdated":null,"targetAudiences":["All people who care about unnecessary deaths","Anyone and everyone who wants to contribute"],"tags":["Teaching \u0026 Academics","Humanities"],"rating":{"count":1,"averageValue":"5.0"},"instructors":[{"name":"Chris Sivewright","url":"/user/chris-bankes-sivewright/","totalNumberOfStudents":153252,"totalNumberOfReviews":4905,"averageRating":4.37006769296636}]},"isAlreadyAFreeCourse":false,"couponData":{"couponCode":"UKRAIN2022","originalPrice":"\u20B9799","discountedPrice":"Free","expirationText":"3 days","discountPercentage":100}},"https://www.udemy.com/course/scrum-developer-practice-examen-2022/":{"courseDetails":{"courseId":4714234,"title":"Scrum Developer Practice Examen 2022","shortDescription":"Scrum Developer Practice Examen 2022","longDescription":null,"language":"Espa\u00F1ol","courseUri":"https://www.udemy.com/course/scrum-developer-practice-examen-2022/","imageUri":"https://img-c.udemycdn.com/course/750x422/4714234_f672.jpg","duration":"130 questions","enrolledStudentsCount":"342 estudiantes","lastUpdated":null,"targetAudiences":["Quienes quieran aprender mas sobre metodolog\u00EDas \u00E1giles."],"tags":["Inform\u00E1tica y software","Certificaciones de inform\u00E1tica","Professsional Scrum Developer (PSD)"],"rating":null,"instructors":[{"name":"University Certification","url":"/user/ucert-2/","totalNumberOfStudents":12004,"totalNumberOfReviews":11,"averageRating":4.202157490909091}]},"isAlreadyAFreeCourse":false,"couponData":{"couponCode":"76F84F7B25044DA17F42","originalPrice":"799\u00A0INR","discountedPrice":"Gratis","expirationText":"4 d\u00EDas","discountPercentage":100}},"https://www.udemy.com/course/cryptocurrency-trading-course-for-beginners/":{"courseDetails":{"courseId":4149374,"title":"Cryptocurrency Trading for Beginners (Learn CLICK-BY-CLICK)","shortDescription":"Learn CLICK-BY-CLICK How to Do Cryptocurrency Trading  Even as a Complete Beginner!","longDescription":null,"language":"English","courseUri":"https://www.udemy.com/course/cryptocurrency-trading-course-for-beginners/","imageUri":"https://img-b.udemycdn.com/course/750x422/4149374_7a54_3.jpg","duration":"3 total hours","enrolledStudentsCount":"29,040 students","lastUpdated":null,"targetAudiences":["Anyone who wants to learn more about cryptocurrencies","Anyone who wants to learn more about trading"],"tags":["Finance \u0026 Accounting","Cryptocurrency \u0026 Blockchain","Cryptocurrency"],"rating":{"count":186,"averageValue":"3.9"},"instructors":[{"name":"Roope Kiuttu","url":"/user/roope-kiuttu/","totalNumberOfStudents":485479,"totalNumberOfReviews":9844,"averageRating":3.988063969984202}]},"isAlreadyAFreeCourse":false,"couponData":{"couponCode":"CBF0E72D414581C07BC1","originalPrice":"\u20B97,900","discountedPrice":"Free","expirationText":"4 days","discountPercentage":100}},"https://www.udemy.com/course/css-bootstrap-javascript-and-php-stack-complete-course/":{"courseDetails":{"courseId":4435576,"title":"CSS, Bootstrap, JavaScript And PHP Stack Complete Course","shortDescription":"CSS, Bootstrap And JavaScript And PHP Complete Frontend and Backend Course","longDescription":null,"language":"English","courseUri":"https://www.udemy.com/course/css-bootstrap-javascript-and-php-stack-complete-course/","imageUri":"https://img-b.udemycdn.com/course/750x422/4435576_a1dc.jpg","duration":"8 total hours","enrolledStudentsCount":"18,014 students","lastUpdated":null,"targetAudiences":["Beginner Full Stack Developers","Beginner Web Developer"],"tags":["Development","Web Development","JavaScript"],"rating":{"count":64,"averageValue":"4.4"},"instructors":[{"name":"PROPER DOT INSTITUTE","url":"/user/vivek-dahibhate-2/","totalNumberOfStudents":181071,"totalNumberOfReviews":2613,"averageRating":4.2814068478557505}]},"isAlreadyAFreeCourse":false,"couponData":{"couponCode":"A6F976C246D5412BCE7C","originalPrice":"\u20B96,500","discountedPrice":"Free","expirationText":"4 days","discountPercentage":100}},"https://www.udemy.com/course/complete-cubase-megacourse-beginner-to-expert/":{"courseDetails":{"courseId":4421602,"title":"Complete Cubase Megacourse: Beginner to Expert","shortDescription":"Learn how to create and edit music like a pro with this step-by-step course!","longDescription":null,"language":"English","courseUri":"https://www.udemy.com/course/complete-cubase-megacourse-beginner-to-expert/","imageUri":"https://img-b.udemycdn.com/course/750x422/4421602_4a17.jpg","duration":"9 total hours","enrolledStudentsCount":"11,999 students","lastUpdated":null,"targetAudiences":["Anyone who wants to learn to create music - no experience needed!","Musicians who want to learn new styles","Musicians who want to learn the basics of a new DAW","Anyone with specialised needs (DJs, producers, musicians, audio editors)"],"tags":["Music","Music Production","Cubase"],"rating":{"count":36,"averageValue":"4.4"},"instructors":[{"name":"Creativity Unleashed","url":"/user/creativity-unleashed/","totalNumberOfStudents":138833,"totalNumberOfReviews":1991,"averageRating":4.422175433246753}]},"isAlreadyAFreeCourse":false,"couponData":{"couponCode":"35168CA90E0A1A1BE018","originalPrice":"\u20B9799","discountedPrice":"Free","expirationText":"4 days","discountPercentage":100}},"https://www.udemy.com/course/excel-pivot-tabellen/":{"courseDetails":{"courseId":2307974,"title":"Microsoft Excel Pivot-Tabellen f\u00FCr Job und Beruf","shortDescription":"Lerne, wie Du mit Pivot-Tabellen gro\u00DFe Datenmengen zusammenfassen und professionelle Reports erstellen kannst!","longDescription":null,"language":"Deutsch","courseUri":"https://www.udemy.com/course/excel-pivot-tabellen/","imageUri":"https://img-b.udemycdn.com/course/750x422/2307974_8bf4_7.jpg","duration":"3.5 total hours","enrolledStudentsCount":"1.956 Teilnehmer","lastUpdated":null,"targetAudiences":["Du bist in Deinem Job auf Microsoft Excel angewiesen...","Oder Du besch\u00E4ftigst Dich privat oder hobbym\u00E4\u00DFig mit Excel","Du hast ab und zu mit gr\u00F6\u00DFeren Tabellen zu tun","Du willst enorm viel Zeit sparen im B\u00FCro, damit unabk\u00F6mmlich sein und Dir die besseren Jobs angeln"],"tags":["Office-Produktivit\u00E4t","Microsoft","Excel"],"rating":{"count":55,"averageValue":"4.3"},"instructors":[{"name":"Sebastian Gl\u00F6ckner","url":"/user/sebastianglckner/","totalNumberOfStudents":197172,"totalNumberOfReviews":13236,"averageRating":4.463702378068094},{"name":"Sebastian Gl\u00F6ckner Karriere-Entwicklung","url":"/user/sebastian-glockner-office-produktivitat/","totalNumberOfStudents":85903,"totalNumberOfReviews":8093,"averageRating":4.69373321292683}]},"isAlreadyAFreeCourse":false,"couponData":{"couponCode":"E60A6BECA715F70C88E9","originalPrice":"7.900\u00A0\u20B9","discountedPrice":"Kostenlos","expirationText":"4 Tage","discountPercentage":100}},"https://www.udemy.com/course/az-500-microsoft-azure-security-technologies-practice-exam-r/":{"courseDetails":{"courseId":4654824,"title":"AZ-500: Microsoft Azure Security Technologies Practice Exam","shortDescription":"AZ-500: Microsoft Azure Security Technologies Practice Exam-2022","longDescription":null,"language":"Espa\u00F1ol","courseUri":"https://www.udemy.com/course/az-500-microsoft-azure-security-technologies-practice-exam-r/","imageUri":"https://img-c.udemycdn.com/course/750x422/4654824_3722_3.jpg","duration":"178 questions","enrolledStudentsCount":"1.041 estudiantes","lastUpdated":null,"targetAudiences":["Cualquiera que necesite convertirse en un mejor examinador antes de intentar el examen de certificaci\u00F3n AZ-500."],"tags":["Inform\u00E1tica y software","Certificaciones de inform\u00E1tica","Certificaci\u00F3n Microsoft"],"rating":null,"instructors":[{"name":"Carlos Alberto Ca\u00F1\u00F3n Romero","url":"/user/carlos-alberto-canon-romero/","totalNumberOfStudents":55059,"totalNumberOfReviews":1032,"averageRating":4.3028511229166675}]},"isAlreadyAFreeCourse":false,"couponData":{"couponCode":"E0AEF4664330E53DB5D5","originalPrice":"799\u00A0INR","discountedPrice":"Gratis","expirationText":"4 d\u00EDas","discountPercentage":100}},"https://www.udemy.com/course/startups-mini-course/":{"courseDetails":{"courseId":3679228,"title":"Startup Bootstrapping Mastery 2022","shortDescription":"How to bootstrap a startup business with minimum costs and secure funding without giving away the rights to your company","longDescription":null,"language":"English","courseUri":"https://www.udemy.com/course/startups-mini-course/","imageUri":"https://img-b.udemycdn.com/course/750x422/3679228_d32b_5.jpg","duration":"44 total mins","enrolledStudentsCount":"18,993 students","lastUpdated":null,"targetAudiences":["Anyone Who Wants to Make Money Online Starting their own companies","Anyone Who Wants Additional Passive Income Streams","Anyone Who Wants to Fire Their Boss"],"tags":["Business","Entrepreneurship","Entrepreneurship Fundamentals"],"rating":{"count":27,"averageValue":"4.3"},"instructors":[{"name":"Henry Zhang","url":"/user/henry-zhang-26/","totalNumberOfStudents":200752,"totalNumberOfReviews":3343,"averageRating":3.936086841116752},{"name":"Henry Zhang Support","url":"/user/henry-zhang-support/","totalNumberOfStudents":200752,"totalNumberOfReviews":3343,"averageRating":3.936086841116752}]},"isAlreadyAFreeCourse":false,"couponData":{"couponCode":"E4EFF78F61B3F2AB40E6","originalPrice":"\u20B93,399","discountedPrice":"Free","expirationText":"3 days","discountPercentage":100}},"https://www.udemy.com/course/social-psychology-understanding-group-behavior/":{"courseDetails":{"courseId":4358978,"title":"Group Dynamics: Psychology of Group Behavior","shortDescription":"Become an expert in group behavior! Learn how every group is similar in form and development and how each one operates.","longDescription":null,"language":"English","courseUri":"https://www.udemy.com/course/social-psychology-understanding-group-behavior/","imageUri":"https://img-b.udemycdn.com/course/750x422/4358978_f2f4_2.jpg","duration":"6 total hours","enrolledStudentsCount":"3,093 students","lastUpdated":null,"targetAudiences":["Managers, employees, teachers, or anyone that spends large amounts of time with other people","Psychology students that want to supplement their understanding of social psychology","Those who wish to gain an advantage in their social world by gaining insight into how group behavior is structured"],"tags":["Teaching \u0026 Academics","Social Science","Social Psychology"],"rating":{"count":10,"averageValue":"4.5"},"instructors":[{"name":"Taylor Guthrie","url":"/user/taylor-guthrie-7/","totalNumberOfStudents":3093,"totalNumberOfReviews":10,"averageRating":4.498113}]},"isAlreadyAFreeCourse":false,"couponData":{"couponCode":"A206A766201CCEBA7D8B","originalPrice":"\u20B92,299","discountedPrice":"Free","expirationText":"4 days","discountPercentage":100}},"https://www.udemy.com/course/complete-clip-studio-paint-megacourse-beginner-to-expert/":{"courseDetails":{"courseId":4357748,"title":"Complete Clip Studio Paint Megacourse: Beginner to Expert","shortDescription":"Learn how to create digital art and illustrate like a pro with this step-by-step course!","longDescription":null,"language":"English","courseUri":"https://www.udemy.com/course/complete-clip-studio-paint-megacourse-beginner-to-expert/","imageUri":"https://img-b.udemycdn.com/course/750x422/4357748_4250.jpg","duration":"12.5 total hours","enrolledStudentsCount":"19,442 students","lastUpdated":null,"targetAudiences":["Anyone who wants to learn to create digital art - no experience needed!","Artists/designers who want to learn new styles","Anyone with specialised needs (cartoonists, digital artists, illustrators, animators)"],"tags":["Design","Graphic Design \u0026 Illustration","Clip Studio Paint"],"rating":{"count":63,"averageValue":"4.1"},"instructors":[{"name":"Creativity Unleashed","url":"/user/creativity-unleashed/","totalNumberOfStudents":138833,"totalNumberOfReviews":1991,"averageRating":4.422175433246753}]},"isAlreadyAFreeCourse":false,"couponData":{"couponCode":"5CE8046A686DAA7C2FE5","originalPrice":"\u20B9799","discountedPrice":"Free","expirationText":"4 days","discountPercentage":100}},"https://www.udemy.com/course/three-cs-to-success/":{"courseDetails":{"courseId":4716276,"title":"Three C\u0027s to Success","shortDescription":"A step by step formula to creating lasting change and living a life you are proud of.","longDescription":null,"language":"English","courseUri":"https://www.udemy.com/course/three-cs-to-success/","imageUri":"https://img-b.udemycdn.com/course/750x422/4716276_c99d_5.jpg","duration":"1.5 total hours","enrolledStudentsCount":"115 students","lastUpdated":null,"targetAudiences":["This course is for anyone with a burning desire for making any kind of change in their life - big or small. I give you the simple but effective tools to help you get to a place in your life where you will be confident in who you are, the REAL, most AUTHENTIC version of YOU."],"tags":["Personal Development","Personal Transformation","Confidence"],"rating":null,"instructors":[{"name":"Kristy Lange","url":"/user/kristy-lange/","totalNumberOfStudents":112,"totalNumberOfReviews":0,"averageRating":0}]},"isAlreadyAFreeCourse":false,"couponData":{"couponCode":"MAKEACHANGE","originalPrice":"\u20B91,299","discountedPrice":"Free","expirationText":"4 days","discountPercentage":100}},"https://www.udemy.com/course/solana-blockchain-developer/":{"courseDetails":{"courseId":4613764,"title":"Solana Blockchain Developer Foundation - Rust and Typescript","shortDescription":"Create dApps, Defi, NFTs, Solana Tokens. With Web3.js, Metaplex, Smart Contracts, React, Typescript","longDescription":null,"language":"English","courseUri":"https://www.udemy.com/course/solana-blockchain-developer/","imageUri":"https://img-b.udemycdn.com/course/750x422/4613764_8516_8.jpg","duration":"6 total hours","enrolledStudentsCount":"485 students","lastUpdated":null,"targetAudiences":["Beginner Programmers wanting to become Blockchain Developers."],"tags":["Finance \u0026 Accounting","Cryptocurrency \u0026 Blockchain","Blockchain"],"rating":{"count":15,"averageValue":"3.6"},"instructors":[{"name":"Serpent Academy","url":"/user/pablo-fabre-5/","totalNumberOfStudents":485,"totalNumberOfReviews":15,"averageRating":3.6077743}]},"isAlreadyAFreeCourse":false,"couponData":{"couponCode":"03FB875091778F392D7B","originalPrice":"\u20B92,599","discountedPrice":"Free","expirationText":"4 days","discountPercentage":100}},"https://www.udemy.com/course/python-and-flask-only-demonstration-course/":{"courseDetails":{"courseId":3526008,"title":"Python And Flask  Demonstrations Practice Course","shortDescription":"This course is a Great Practice to both fundamental python programming concepts and the Flask Framework by demonstration","longDescription":null,"language":"English","courseUri":"https://www.udemy.com/course/python-and-flask-only-demonstration-course/","imageUri":"https://img-b.udemycdn.com/course/750x422/3526008_d891_5.jpg","duration":"8 total hours","enrolledStudentsCount":"134,817 students","lastUpdated":null,"targetAudiences":["For Python Programming Learners","For People Who want to learn Python Fundamentals and later transition into Data Science or Web Development"],"tags":["IT \u0026 Software","IT Certifications","Flask"],"rating":{"count":541,"averageValue":"4.4"},"instructors":[{"name":"Horizon Tech","url":"/user/suraj-g-nimbalkar/","totalNumberOfStudents":707878,"totalNumberOfReviews":10965,"averageRating":4.2131702755165295}]},"isAlreadyAFreeCourse":false,"couponData":{"couponCode":"50708B6740F27EAE662B","originalPrice":"\u20B91,499","discountedPrice":"Free","expirationText":"4 days","discountPercentage":100}},"https://www.udemy.com/course/sql-desde-cero-curso-practico/":{"courseDetails":{"courseId":1786172,"title":"SQL B\u00E1sico - Intermedio \u00A1A\u00F1ade valor a tu CV en 2 horas!","shortDescription":"Aprende SQL desde cero para manejar bases de datos y grandes cantidades de informaci\u00F3n.","longDescription":null,"language":"Spanish","courseUri":"https://www.udemy.com/course/sql-desde-cero-curso-practico/","imageUri":"https://img-c.udemycdn.com/course/750x422/1786172_2c2f_4.jpg","duration":"1.5 total hours","enrolledStudentsCount":"57,770 students","lastUpdated":null,"targetAudiences":["Est\u00E1 dirigido a quienes dan sus primeros pasos hacia una formaci\u00F3n de Data Analyst (Analista de datos), Data Scientist (Cient\u00EDfico de Datos) o de DBA (Data Base Administrador - Administrador de Bases de Datos)."],"tags":["Development","Database Design \u0026 Development","SQL"],"rating":{"count":2512,"averageValue":"4.5"},"instructors":[{"name":"Ra\u00FAl Montesinos","url":"/user/ralmontesinos/","totalNumberOfStudents":349839,"totalNumberOfReviews":11787,"averageRating":4.3623648394262045},{"name":"Numpi Cursos","url":"/user/numpi/","totalNumberOfStudents":340365,"totalNumberOfReviews":26161,"averageRating":4.369865950227754}]},"isAlreadyAFreeCourse":false,"couponData":{"couponCode":"BDED1B695BEF71A10EDC","originalPrice":"\u20B91,999","discountedPrice":"\u20B91,299","expirationText":"14 hours","discountPercentage":35}},"https://www.udemy.com/course/ultimate-watercolor-techniques-figure-to-landscape-painting/":{"courseDetails":{"courseId":4665572,"title":"Ultimate Watercolor Techniques: Figure to Landscape Painting","shortDescription":"From the basics to complete artworks","longDescription":null,"language":"English","courseUri":"https://www.udemy.com/course/ultimate-watercolor-techniques-figure-to-landscape-painting/","imageUri":"https://img-c.udemycdn.com/course/750x422/4665572_76be.jpg","duration":"4 total hours","enrolledStudentsCount":"1,108 students","lastUpdated":null,"targetAudiences":["Art lovers","Students","Anyone who wants to learn watercolor!"],"tags":["Lifestyle","Arts \u0026 Crafts","Watercolor Painting"],"rating":{"count":2,"averageValue":"5.0"},"instructors":[{"name":"Ava Moradi","url":"/user/ava-moradi-2/","totalNumberOfStudents":30436,"totalNumberOfReviews":1677,"averageRating":4.6995109009345795}]},"isAlreadyAFreeCourse":false,"couponData":{"couponCode":"FREECOURSE2","originalPrice":"\u20B91,499","discountedPrice":"\u20B9999","expirationText":"14 hours","discountPercentage":33}},"https://www.udemy.com/course/complete-revit-guide-project-documentation-essentials/":{"courseDetails":{"courseId":4719488,"title":"Complete Revit Guide - Project Documentation Essentials","shortDescription":"Develop Quality Sections, Details, Cost Estimates and Schedules in Revit","longDescription":null,"language":"English","courseUri":"https://www.udemy.com/course/complete-revit-guide-project-documentation-essentials/","imageUri":"https://img-c.udemycdn.com/course/750x422/4719488_1be8.jpg","duration":"3.5 total hours","enrolledStudentsCount":"102 students","lastUpdated":null,"targetAudiences":["Architects, Designers, Engineers, Building professionals"],"tags":["Design","Architectural Design","Revit"],"rating":null,"instructors":[{"name":"Brandon Aaron","url":"/user/brandonagibbs/","totalNumberOfStudents":7754,"totalNumberOfReviews":164,"averageRating":4.530433331325302}]},"isAlreadyAFreeCourse":false,"couponData":{"couponCode":"B20B102E1B93DF9424C8","originalPrice":"\u20B93,399","discountedPrice":"\u20B92,299","expirationText":"14 hours","discountPercentage":32}},"https://www.udemy.com/course/microsoft-excel-de-cero-a-analista-de-datos-en-power-bi/":{"courseDetails":{"courseId":4270096,"title":"Microsoft Excel: De cero a analista de datos en Power BI","shortDescription":"El curso te dar\u00E1 un dominio completo de Microsoft Excel y te introducir\u00E1 a la inteligencia de negocio.","longDescription":null,"language":"Spanish","courseUri":"https://www.udemy.com/course/microsoft-excel-de-cero-a-analista-de-datos-en-power-bi/","imageUri":"https://img-c.udemycdn.com/course/750x422/4270096_4f89_9.jpg","duration":"6 total hours","enrolledStudentsCount":"30,536 students","lastUpdated":null,"targetAudiences":["Toda persona que necesite aprender y/o dominar Microsoft Excel ya sea de forma educativa o profesional.","Profesionistas que necesiten mejorar sus productividad en la oficina.","Profesionistas que requieran trabajar con una gran cantidad de datos."],"tags":["Business","Business Analytics \u0026 Intelligence","Excel VBA"],"rating":{"count":495,"averageValue":"4.2"},"instructors":[{"name":"Numpi Cursos","url":"/user/numpi/","totalNumberOfStudents":340365,"totalNumberOfReviews":26161,"averageRating":4.369865950227754},{"name":"Hugo Aguilar Svonik","url":"/user/hugo-aguilar-svonik/","totalNumberOfStudents":32298,"totalNumberOfReviews":540,"averageRating":4.305884436690647}]},"isAlreadyAFreeCourse":false,"couponData":{"couponCode":"4F529EE07C6AA7444B3E","originalPrice":"\u20B93,899","discountedPrice":"\u20B92,699","expirationText":"14 hours","discountPercentage":31}},"https://www.udemy.com/course/mongodb-aprende-desde-cero/":{"courseDetails":{"courseId":4110700,"title":"MongoDB: Aprende desde cero a experto","shortDescription":"Vuelvete un experto en Bases de Datos no relacionales aprendiendo de una manera f\u00E1cil y sencilla.","longDescription":null,"language":"Spanish","courseUri":"https://www.udemy.com/course/mongodb-aprende-desde-cero/","imageUri":"https://img-c.udemycdn.com/course/750x422/4110700_b686_17.jpg","duration":"7.5 total hours","enrolledStudentsCount":"73,807 students","lastUpdated":null,"targetAudiences":["Personas que quieran dominar las bases de datos NoSQL con MongoDB.","Personas que quieran iniciarse en el mundo del Big Data y el Data Science.","Personas que quieran expandir sus conocimientos acerca de las bases de datos."],"tags":["Development","Database Design \u0026 Development","MongoDB"],"rating":{"count":713,"averageValue":"4.3"},"instructors":[{"name":"Numpi Cursos","url":"/user/numpi/","totalNumberOfStudents":340365,"totalNumberOfReviews":26161,"averageRating":4.369865950227754}]},"isAlreadyAFreeCourse":false,"couponData":{"couponCode":"54CDDF456C09B887DD2B","originalPrice":"\u20B93,899","discountedPrice":"\u20B92,699","expirationText":"14 hours","discountPercentage":31}},"https://www.udemy.com/course/aprende-sql-desde-cero-curso-con-mas-de-100-ejercicios/":{"courseDetails":{"courseId":3756262,"title":"SQL: Consultas b\u00E1sicas a complejas","shortDescription":"Aprender\u00E1s a consultar y modificar informaci\u00F3n de una base de datos. \u00A1Curso con m\u00E1s de 100 ejercicios!","longDescription":null,"language":"Spanish","courseUri":"https://www.udemy.com/course/aprende-sql-desde-cero-curso-con-mas-de-100-ejercicios/","imageUri":"https://img-c.udemycdn.com/course/750x422/3756262_f347_20.jpg","duration":"2 total hours","enrolledStudentsCount":"97,136 students","lastUpdated":null,"targetAudiences":["Cualquier persona interesada en aprender m\u00E1s sobre SQL o an\u00E1lisis de datos.","Estudiantes y profesionistas que desean ampliar sus conocimientos en MySQL y lograr ser expertos en la materia.","Estudiantes y profesionistas que ya han visto o tienen conocimientos b\u00E1sicos de bases de datos ya que aqu\u00ED se ver\u00E1n temas muy avanzados para facilitarte tus labores en el d\u00EDa a d\u00EDa en el uso de bases de datos."],"tags":["Development","Database Design \u0026 Development","SQL"],"rating":{"count":1979,"averageValue":"4.4"},"instructors":[{"name":"Ra\u00FAl Montesinos","url":"/user/ralmontesinos/","totalNumberOfStudents":349839,"totalNumberOfReviews":11787,"averageRating":4.3623648394262045},{"name":"Numpi Cursos","url":"/user/numpi/","totalNumberOfStudents":340365,"totalNumberOfReviews":26161,"averageRating":4.369865950227754}]},"isAlreadyAFreeCourse":false,"couponData":{"couponCode":"D35641FAC1A36CBEBE4B","originalPrice":"\u20B93,899","discountedPrice":"\u20B92,699","expirationText":"14 hours","discountPercentage":31}},"https://www.udemy.com/course/java-empieza-desde-cero-con-intellij/":{"courseDetails":{"courseId":4004902,"title":"JAVA: Empieza desde cero con IntelliJ","shortDescription":"Aprende f\u00E1cil y divertido todo lo necesario para dominar Java.","longDescription":null,"language":"Espa\u00F1ol","courseUri":"https://www.udemy.com/course/java-empieza-desde-cero-con-intellij/","imageUri":"https://img-c.udemycdn.com/course/750x422/4004902_d281_10.jpg","duration":"3.5 total hours","enrolledStudentsCount":"30.734 estudiantes","lastUpdated":null,"targetAudiences":["Profesionistas que quieran aprender a programar en Java.","Desarrolladores que quieran aprender Java de una manera \u00E1gil, completa y sencilla.","Profesionistas que requieran desarrollar en Java."],"tags":["Desarrollo","Lenguajes de programaci\u00F3n","IntelliJ"],"rating":{"count":286,"averageValue":"4.5"},"instructors":[{"name":"Numpi Cursos","url":"/user/numpi/","totalNumberOfStudents":340365,"totalNumberOfReviews":26161,"averageRating":4.369865950227754}]},"isAlreadyAFreeCourse":false,"couponData":{"couponCode":"2A8D541D38D564EB8B93","originalPrice":"3.899\u00A0INR","discountedPrice":"2.699\u00A0INR","expirationText":"14 horas","discountPercentage":31}},"https://www.udemy.com/course/python-3-analisis-y-visualizacion-de-datos/":{"courseDetails":{"courseId":3655814,"title":"Python 3: An\u00E1lisis y visualizaci\u00F3n de datos","shortDescription":"Comienza en el mundo del an\u00E1lisis de datos y a\u00F1ade valor a tu CV","longDescription":null,"language":"Spanish","courseUri":"https://www.udemy.com/course/python-3-analisis-y-visualizacion-de-datos/","imageUri":"https://img-c.udemycdn.com/course/750x422/3655814_50f2_20.jpg","duration":"7 total hours","enrolledStudentsCount":"69,403 students","lastUpdated":null,"targetAudiences":["Profesionistas que requieran trabajar con una gran cantidad de datos.","Profesionistas que necesiten analizar grandes vol\u00FAmenes de datos."],"tags":["Development","Data Science","Python"],"rating":{"count":529,"averageValue":"4.2"},"instructors":[{"name":"Numpi Cursos","url":"/user/numpi/","totalNumberOfStudents":340365,"totalNumberOfReviews":26161,"averageRating":4.369865950227754}]},"isAlreadyAFreeCourse":false,"couponData":{"couponCode":"6390668FCF3B7F704FE7","originalPrice":"\u20B93,899","discountedPrice":"\u20B92,699","expirationText":"14 hours","discountPercentage":31}},"https://www.udemy.com/course/google-data-studio-desde-cero-para-principiantes/":{"courseDetails":{"courseId":4555396,"title":"An\u00E1lisis de datos con Google Data Studio","shortDescription":"Juan, con experiencia en an\u00E1lisis de datos, te ense\u00F1ar\u00E1 una de las herramientas mas demandadas en el an\u00E1lisis de datos","longDescription":null,"language":"Spanish","courseUri":"https://www.udemy.com/course/google-data-studio-desde-cero-para-principiantes/","imageUri":"https://img-c.udemycdn.com/course/750x422/4555396_1c59_3.jpg","duration":"3 total hours","enrolledStudentsCount":"6,452 students","lastUpdated":null,"targetAudiences":["Estudiantes y profesionales que quieran entrar en el mundo de los datos y el Business Intelligence."],"tags":["Business","Business Analytics \u0026 Intelligence","Google Data Studio"],"rating":{"count":25,"averageValue":"4.3"},"instructors":[{"name":"Numpi Cursos","url":"/user/numpi/","totalNumberOfStudents":340365,"totalNumberOfReviews":26161,"averageRating":4.369865950227754}]},"isAlreadyAFreeCourse":false,"couponData":{"couponCode":"9DF773AB5149E27E380C","originalPrice":"\u20B9799","discountedPrice":"\u20B9560","expirationText":"14 hours","discountPercentage":30}},"https://www.udemy.com/course/aprende-las-bases-de-programacion-con-c/":{"courseDetails":{"courseId":3949466,"title":"Aprende C en 2 horas","shortDescription":"Aprende a programar y desarrollar l\u00F3gica con C","longDescription":null,"language":"Espa\u00F1ol","courseUri":"https://www.udemy.com/course/aprende-las-bases-de-programacion-con-c/","imageUri":"https://img-c.udemycdn.com/course/750x422/3949466_46b1_2.jpg","duration":"2 total hours","enrolledStudentsCount":"8.658 estudiantes","lastUpdated":null,"targetAudiences":["Personas que quieran empezar en el mundo de la programaci\u00F3n"],"tags":["Inform\u00E1tica y software","Inform\u00E1tica y software, otros","Programaci\u00F3n funcional"],"rating":{"count":61,"averageValue":"3.7"},"instructors":[{"name":"Aldo Tob\u00F3n Hel\u00FA","url":"/user/aldo-tobon-helu-3/","totalNumberOfStudents":8652,"totalNumberOfReviews":61,"averageRating":3.7138722}]},"isAlreadyAFreeCourse":false,"couponData":{"couponCode":"4FF42DD2DBA50152708C","originalPrice":"799\u00A0INR","discountedPrice":"560\u00A0INR","expirationText":"14 horas","discountPercentage":30}},"https://www.udemy.com/course/fundamentos-de-programacion-r/":{"courseDetails":{"courseId":4586338,"title":"Fundamentos de Programaci\u00F3n: Aprende a programar desde cero","shortDescription":"De la teor\u00EDa a la pr\u00E1ctica","longDescription":null,"language":"Espa\u00F1ol","courseUri":"https://www.udemy.com/course/fundamentos-de-programacion-r/","imageUri":"https://img-c.udemycdn.com/course/750x422/4586338_dee3_2.jpg","duration":"3.5 total hours","enrolledStudentsCount":"5.669 estudiantes","lastUpdated":null,"targetAudiences":["El curso est\u00E1 dirigido a los estudiantes que quieran comenzar a trabajar en el mundo del desarrollo de software"],"tags":["Inform\u00E1tica y software","Inform\u00E1tica y software, otros","Programaci\u00F3n gen\u00E9rica"],"rating":{"count":45,"averageValue":"4.6"},"instructors":[{"name":"Numpi Cursos","url":"/user/numpi/","totalNumberOfStudents":340365,"totalNumberOfReviews":26161,"averageRating":4.369865950227754},{"name":"Hugo Aguilar Svonik","url":"/user/hugo-aguilar-svonik/","totalNumberOfStudents":32298,"totalNumberOfReviews":540,"averageRating":4.305884436690647}]},"isAlreadyAFreeCourse":false,"couponData":{"couponCode":"94FC854F0D4B89CDBB89","originalPrice":"3.699\u00A0INR","discountedPrice":"2.599\u00A0INR","expirationText":"14 horas","discountPercentage":30}},"https://www.udemy.com/course/usability-testing-user-research-ux-design-evaluation/":{"courseDetails":{"courseId":4485620,"title":"Usability Testing in UX Research \u0026 Design Evaluation (2022)","shortDescription":"Understand, plan \u0026 execute usability test of user interfaces (UI) in UX Design process with hands-on exercises","longDescription":null,"language":"English","courseUri":"https://www.udemy.com/course/usability-testing-user-research-ux-design-evaluation/","imageUri":"https://img-c.udemycdn.com/course/750x422/4485620_a27d.jpg","duration":"1.5 total hours","enrolledStudentsCount":"299 students","lastUpdated":null,"targetAudiences":["Designers who want hands-on techniques for evaluating their designs with end users of mobile apps or websites (including UI/UX Designers, UX researchers, Graphics \u0026 Visual designers)","Students aspiring to start a career in User Experience field.","Junior designers who want to upskill themselves in the principles of Usability Testing for career growth.","Product Managers (PMs) and founders who want to choose the right usability test for the current product lifecycle stage, and validate the designs before development.","Product Marketing Managers who want to understand user behaviour for reducing drop rates or churn, increase conversion \u0026 retention rates and drive optimal product positioning."],"tags":["Design","User Experience Design","Usability Testing"],"rating":{"count":14,"averageValue":"4.8"},"instructors":[{"name":"Nancy Jain","url":"/user/nancyjain3/","totalNumberOfStudents":299,"totalNumberOfReviews":14,"averageRating":4.77752}]},"isAlreadyAFreeCourse":false,"couponData":{"couponCode":"JUN2022FREE","originalPrice":"\u20B9799","discountedPrice":"\u20B9560","expirationText":"14 hours","discountPercentage":30}},"https://www.udemy.com/course/javascript-desde-cero-con-nodejs/":{"courseDetails":{"courseId":4339782,"title":"JavaScript: Desde cero con NodeJS","shortDescription":"Aprende los fundamentos y crea un proyecto REST API con Node JS.","longDescription":null,"language":"Espa\u00F1ol","courseUri":"https://www.udemy.com/course/javascript-desde-cero-con-nodejs/","imageUri":"https://img-c.udemycdn.com/course/750x422/4339782_ca13_7.jpg","duration":"12 total hours","enrolledStudentsCount":"42.058 estudiantes","lastUpdated":null,"targetAudiences":["Cualquier interesado en aprender los fundamentos de este hermoso lenguaje.","Cualquier interesado en aprender a desarrollar aplicaciones JavaScript del lado del servidor."],"tags":["Desarrollo","Herramientas de desarrollo de software","JavaScript"],"rating":{"count":652,"averageValue":"4.7"},"instructors":[{"name":"Numpi Cursos","url":"/user/numpi/","totalNumberOfStudents":340365,"totalNumberOfReviews":26161,"averageRating":4.369865950227754},{"name":"Geovanny Gabriel","url":"/user/geovanny-gabriel/","totalNumberOfStudents":42058,"totalNumberOfReviews":652,"averageRating":4.6876073}]},"isAlreadyAFreeCourse":false,"couponData":{"couponCode":"2F833E949CBB5237CB6B","originalPrice":"3.699\u00A0INR","discountedPrice":"2.599\u00A0INR","expirationText":"14 horas","discountPercentage":30}},"https://www.udemy.com/course/html5-css3-sifirdan-frontend-web-tasarim-gelistirme-kursu/":{"courseDetails":{"courseId":3085050,"title":"HTML5\u002BCSS3\u002BBootstrap \u002B Tailwind CSS v3 Web Geli\u015Ftirme Kursu","shortDescription":"HTML5, CSS3, Flexbox, Bootstrap 4 ve Tailwind CSS v3(React) ile web tasar\u0131m kursu. s\u0131f\u0131rdan frontend projeleri geli\u015Ftir.","longDescription":null,"language":"T\u00FCrk\u00E7e","courseUri":"https://www.udemy.com/course/html5-css3-sifirdan-frontend-web-tasarim-gelistirme-kursu/","imageUri":"https://img-c.udemycdn.com/course/750x422/3085050_25a4_4.jpg","duration":"19 total hours","enrolledStudentsCount":"6.361 \u00F6\u011Frenci","lastUpdated":null,"targetAudiences":["S\u0131f\u0131rdan web site tasar\u0131m\u0131 yapmak isteyenler.","html ve html5 yap\u0131s\u0131n\u0131 \u00F6\u011Frenmek isteyenler.","Css ve css3 tan\u0131mlamalar\u0131n\u0131 \u00F6\u011Frenmek isteyenler.","Frontend alan\u0131nda kendini yeti\u015Ftirmek isteyenler.","Yaz\u0131l\u0131ma yeni ba\u015Flayanlar ve profesyonel hayata ge\u00E7i\u015F yapmak isteyenler","Bootstrap \u00F6\u011Frenmek isteyenler","Tailwind CSS \u00F6\u011Frenmek isteyenler"],"tags":["Yaz\u0131l\u0131m Geli\u015Ftirme","Web Geli\u015Ftirme","Web Geli\u015Ftirme"],"rating":{"count":248,"averageValue":"4.4"},"instructors":[{"name":"Cihan Ko\u00E7","url":"/user/cihan-koc-4/","totalNumberOfStudents":8753,"totalNumberOfReviews":484,"averageRating":4.659888499999999}]},"isAlreadyAFreeCourse":false,"couponData":{"couponCode":"HAZIRANFREE","originalPrice":"799\u00A0\u20B9","discountedPrice":"560\u00A0\u20B9","expirationText":"14 saat","discountPercentage":30}},"https://www.udemy.com/course/programacion-desarrollo-web/":{"courseDetails":{"courseId":4368122,"title":"Escuela de Programaci\u00F3n y Desarrollo Web desde cero a Master","shortDescription":"Aprende programaci\u00F3n y desarrollo Web desde cero con lenguajes HTML, CSS, JavaScript, Python, Go (Golang) y Java.","longDescription":null,"language":"Espa\u00F1ol","courseUri":"https://www.udemy.com/course/programacion-desarrollo-web/","imageUri":"https://img-c.udemycdn.com/course/750x422/4368122_c5cd.jpg","duration":"65.5 total hours","enrolledStudentsCount":"21.467 estudiantes","lastUpdated":null,"targetAudiences":["Estudiantes que quieran aprender una variedad de lenguajes de programaci\u00F3n como (JavaScript, Python, Go, Java).","Para estudiantes que quieran desarrollar en el lado del Frontend usando HTML, CSS Y JavaScript.","Para estudiantes que quieran desarrollar en el lado del backend usando  framework web como (Node JS, Flask, Django )","Introducirse en el lado del desarrollo web.","Crear tus sitios Web."],"tags":["Desarrollo","Desarrollo web","Desarrollo web"],"rating":{"count":476,"averageValue":"4.5"},"instructors":[{"name":"Roel Code","url":"/user/alex-roel/","totalNumberOfStudents":98685,"totalNumberOfReviews":3765,"averageRating":4.494823218719212}]},"isAlreadyAFreeCourse":false,"couponData":{"couponCode":"E6E9359DE6","originalPrice":"799\u00A0INR","discountedPrice":"560\u00A0INR","expirationText":"14 horas","discountPercentage":30}},"https://www.udemy.com/course/aws-certified-solutions-architect-associate-6practice-tests/":{"courseDetails":{"courseId":4721454,"title":"AWS Certified Solutions Architect-Associate 6Practice Tests","shortDescription":"390\u002B top-quality practice test questions for your AWS SAA-C02 exam | JUNE 2022 UPDATED","longDescription":null,"language":"English","courseUri":"https://www.udemy.com/course/aws-certified-solutions-architect-associate-6practice-tests/","imageUri":"https://img-b.udemycdn.com/course/750x422/4721454_925e.jpg","duration":"390 questions","enrolledStudentsCount":"100 students","lastUpdated":null,"targetAudiences":["AWS Certified Solutions architect Associate Exam candidates and students willing to pass the exam ."],"tags":["IT \u0026 Software","IT Certifications"],"rating":null,"instructors":[{"name":"Mehdi Omari","url":"/user/mehdi-ammel/","totalNumberOfStudents":9751,"totalNumberOfReviews":26,"averageRating":4.130102830769231}]},"isAlreadyAFreeCourse":false,"couponData":{"couponCode":"712F4550CFB719BD15F8","originalPrice":"\u20B9799","discountedPrice":"\u20B9560","expirationText":"14 hours","discountPercentage":30}},"https://www.udemy.com/course/bootstrap-4-egitimi-ile-sifirdan-animasyonlu-responsive-tasarim-yapmak/":{"courseDetails":{"courseId":2184332,"title":"Bootstrap 4 ile S\u0131f\u0131rdan 5 Ger\u00E7ek Web Tasar\u0131m Projesi","shortDescription":"Bootstrap 4 |Html5 ve Css3 Kullanarak Animasyonlu Responsive Web Tasar\u0131m E\u011Fitimi | S\u0131f\u0131rdan Frontend Web Tasar\u0131m E\u011Fitimi","longDescription":null,"language":"T\u00FCrk\u00E7e","courseUri":"https://www.udemy.com/course/bootstrap-4-egitimi-ile-sifirdan-animasyonlu-responsive-tasarim-yapmak/","imageUri":"https://img-c.udemycdn.com/course/750x422/2184332_1795_5.jpg","duration":"18.5 total hours","enrolledStudentsCount":"3.039 \u00F6\u011Frenci","lastUpdated":null,"targetAudiences":["S\u0131f\u0131rdan Bootstrap 4 ile ileri seviye tasar\u0131mlar yapmay\u0131 \u00F6\u011Frenmek isteyenler","Kendi tasar\u0131mlar\u0131n\u0131 kendi yapmak isteyenler.","Frontend yap\u0131s\u0131n\u0131 \u00F6\u011Frenerek ger\u00E7ek projeler geli\u015Ftirmek isteyenler."],"tags":["Yaz\u0131l\u0131m Geli\u015Ftirme","Web Geli\u015Ftirme","Bootstrap"],"rating":{"count":236,"averageValue":"4.9"},"instructors":[{"name":"Cihan Ko\u00E7","url":"/user/cihan-koc-4/","totalNumberOfStudents":8753,"totalNumberOfReviews":484,"averageRating":4.659888499999999}]},"isAlreadyAFreeCourse":false,"couponData":{"couponCode":"HAZIRANFREE","originalPrice":"799\u00A0\u20B9","discountedPrice":"560\u00A0\u20B9","expirationText":"14 saat","discountPercentage":30}}},"freeCourses":{}}