{"coursesWithCoupon":{"https://www.udemy.com/course/a1-german-language-practice-test/":{"courseDetails":{"courseId":4774196,"title":"A1 German Language Practice Test [With FREE E-Book]","shortDescription":"This Course Includes A1/Beginner Level Questions In German Language That Will Help You In Exams \u0026 Real Life.","longDescription":null,"language":"Deutsch","courseUri":"https://www.udemy.com/course/a1-german-language-practice-test/","imageUri":"https://img-c.udemycdn.com/course/750x422/4774196_ba1b.jpg","duration":"40 questions","enrolledStudentsCount":"145 Teilnehmer","lastUpdated":null,"targetAudiences":["Beginner in German Language"],"tags":["Wissenschaft \u0026 Lehre","Sprachen lernen"],"rating":null,"instructors":[{"name":"Bharti Saini","url":"/user/bharti-saini-26/","totalNumberOfStudents":143,"totalNumberOfReviews":0,"averageRating":0}]},"isAlreadyAFreeCourse":false,"couponData":{"couponCode":"8F0473E978DCB62731BE","originalPrice":"799\u00A0\u20B9","discountedPrice":"Kostenlos","expirationText":"4 Tage","discountPercentage":100}},"https://www.udemy.com/course/video-lecture-with-neitdesign-for-invideo/":{"courseDetails":{"courseId":3183184,"title":"Creating Video Lessons with Online Video Maker InVideo","shortDescription":"Learn how to create stunning video lectures using Article-to-Video templates from an online tool InVideo fast and easy!","longDescription":null,"language":"English","courseUri":"https://www.udemy.com/course/video-lecture-with-neitdesign-for-invideo/","imageUri":"https://img-b.udemycdn.com/course/750x422/3183184_0ef7.jpg","duration":"1 total hour","enrolledStudentsCount":"15,712 students","lastUpdated":null,"targetAudiences":["Online educators and coaches","YouTube, Udemy, SkillsShare coaches","Business Trainers","School teachers","College and university professors and lecturers","Auto webinars creators","How To and Useful Tips bloggers"],"tags":["Teaching \u0026 Academics","Online Education","InVideo"],"rating":{"count":67,"averageValue":"4.4"},"instructors":[{"name":"Natalia Lyashenko","url":"/user/065c8734-533e-4fd1-9d38-3a4a2a730357/","totalNumberOfStudents":103866,"totalNumberOfReviews":1530,"averageRating":4.355791520802005}]},"isAlreadyAFreeCourse":false,"couponData":{"couponCode":"INVIDEO_JULY1","originalPrice":"\u20B9799","discountedPrice":"Free","expirationText":"4 days","discountPercentage":100}},"https://www.udemy.com/course/cince-hsk-3-kursu-konu-anlatm-ve-hsk-soru-cozumleri/":{"courseDetails":{"courseId":4656326,"title":"\u00C7ince HSK 3 Kursu: Konu Anlat\u0131m\u0131 ve HSK Soru \u00C7\u00F6z\u00FCmleri","shortDescription":"\u00C7ince HSK 3 S\u0131nav\u0131na Haz\u0131rl\u0131k Kursu, Bu kursla Birlikte HSK 3 S\u0131nav\u0131na Tam Olarak Haz\u0131rlanm\u0131\u015F Olacaks\u0131n\u0131z.","longDescription":null,"language":"T\u00FCrk\u00E7e","courseUri":"https://www.udemy.com/course/cince-hsk-3-kursu-konu-anlatm-ve-hsk-soru-cozumleri/","imageUri":"https://img-c.udemycdn.com/course/750x422/4656326_0fc8.jpg","duration":"19.5 total hours","enrolledStudentsCount":"480 \u00F6\u011Frenci","lastUpdated":null,"targetAudiences":["HSK 3 s\u0131nav\u0131n\u0131 ge\u00E7mek isteyenler i\u00E7in ideal bir kurs."],"tags":["\u00D6\u011Fretim ve Akademi","Dil \u00D6\u011Frenimi","\u00C7ince"],"rating":{"count":67,"averageValue":"5.0"},"instructors":[{"name":"Abdurrahman TEKIN","url":"/user/abdurrahman-tekin/","totalNumberOfStudents":19811,"totalNumberOfReviews":1098,"averageRating":4.719062261916462}]},"isAlreadyAFreeCourse":false,"couponData":{"couponCode":"05F29105989E8CB3D8D4","originalPrice":"799\u00A0\u20B9","discountedPrice":"\u00DCcretsiz","expirationText":"23 saat","discountPercentage":100}},"https://www.udemy.com/course/aws-certified-solutions-architect-associate-practice-exams-new/":{"courseDetails":{"courseId":4686764,"title":"AWS Certified Solutions Architect Associate Practice Exams","shortDescription":"Prepare for AWS Solutions Architect | AWS Certified Solutions Architect Associate [SAA-C02] Practice Tests 2022","longDescription":null,"language":"English","courseUri":"https://www.udemy.com/course/aws-certified-solutions-architect-associate-practice-exams-new/","imageUri":"https://img-c.udemycdn.com/course/750x422/4686764_0887_5.jpg","duration":"125 questions","enrolledStudentsCount":"6,029 students","lastUpdated":null,"targetAudiences":["Anyone, who is preparing for the AWS Certified Solutions Architect - Associate exam SAA-C02","All IT Professionals who want to boost AWS knowledge for AWS Job interview","Students who want to test their knowledge for exams"],"tags":["IT \u0026 Software","IT Certifications","AWS Certification"],"rating":{"count":14,"averageValue":"4.2"},"instructors":[{"name":"Odoben Academy","url":"/user/odoben/","totalNumberOfStudents":19014,"totalNumberOfReviews":125,"averageRating":4.579016460784314}]},"isAlreadyAFreeCourse":false,"couponData":{"couponCode":"AED13E20BD7956EE7D64","originalPrice":"\u20B9799","discountedPrice":"Free","expirationText":"4 days","discountPercentage":100}},"https://www.udemy.com/course/cince-hsk-4-kursu-konu-anlatm-ve-hsk-soru-cozumleri/":{"courseDetails":{"courseId":4657366,"title":"\u00C7ince HSK 4 Kursu: Konu Anlat\u0131m\u0131 ve HSK Soru \u00C7\u00F6z\u00FCmleri","shortDescription":"\u00C7ince HSK 4 S\u0131nav\u0131na Haz\u0131rl\u0131k Kursu, Bu kursla Birlikte HSK 4 S\u0131nav\u0131na Tam Olarak Haz\u0131rlanm\u0131\u015F Olacaks\u0131n\u0131z.","longDescription":null,"language":"T\u00FCrk\u00E7e","courseUri":"https://www.udemy.com/course/cince-hsk-4-kursu-konu-anlatm-ve-hsk-soru-cozumleri/","imageUri":"https://img-c.udemycdn.com/course/750x422/4657366_0f53.jpg","duration":"39 total hours","enrolledStudentsCount":"420 \u00F6\u011Frenci","lastUpdated":null,"targetAudiences":["HSK 4 s\u0131nav\u0131n\u0131 ge\u00E7mek isteyenler i\u00E7in ideal bir kurs."],"tags":["\u00D6\u011Fretim ve Akademi","Dil \u00D6\u011Frenimi","\u00C7ince"],"rating":{"count":43,"averageValue":"5.0"},"instructors":[{"name":"Abdurrahman TEKIN","url":"/user/abdurrahman-tekin/","totalNumberOfStudents":19811,"totalNumberOfReviews":1098,"averageRating":4.719062261916462}]},"isAlreadyAFreeCourse":false,"couponData":{"couponCode":"CCDA1488C0E1B12C10A5","originalPrice":"799\u00A0\u20B9","discountedPrice":"\u00DCcretsiz","expirationText":"23 saat","discountPercentage":100}},"https://www.udemy.com/course/facebook-page-2022/":{"courseDetails":{"courseId":3851762,"title":"Facebook Page \u0026 Facebook Ads Made as Fun: 11 Days Challenge","shortDescription":"Set Up your Facebook Business Page \u0026 Business Manager. Use Facebook Creator Studio. Launch Facebook Ads. Generate Leads.","longDescription":null,"language":"English","courseUri":"https://www.udemy.com/course/facebook-page-2022/","imageUri":"https://img-b.udemycdn.com/course/750x422/3851762_e3b4_3.jpg","duration":"10 total hours","enrolledStudentsCount":"27,375 students","lastUpdated":null,"targetAudiences":["For beginners wishing to follow step by step logical tasks to succeed with Facebook for business."],"tags":["Marketing","Paid Advertising","Facebook Ads"],"rating":{"count":265,"averageValue":"4.2"},"instructors":[{"name":"Ing. Tomas Moravek | Facebook Ads Expert","url":"/user/ing-tomas-moravek-2/","totalNumberOfStudents":686027,"totalNumberOfReviews":17705,"averageRating":4.470362234556747},{"name":"SEO, Facebook Ads \u0026 Digital Marketing Academy","url":"/user/seo-facebook-ads-digital-marketing-academy/","totalNumberOfStudents":685777,"totalNumberOfReviews":17705,"averageRating":4.470362234556747},{"name":"Beck Robertson","url":"/user/beck-robertson-3/","totalNumberOfStudents":619998,"totalNumberOfReviews":15124,"averageRating":4.4828118364206135}]},"isAlreadyAFreeCourse":false,"couponData":{"couponCode":"WATERTIGER7","originalPrice":"\u20B97,900","discountedPrice":"Free","expirationText":"4 days","discountPercentage":100}},"https://www.udemy.com/course/strategic-ways-to-build-your-business-with-youtube/":{"courseDetails":{"courseId":417284,"title":"Strategic Ways to Build a Successful Business on Youtube!","shortDescription":"Your complete guide to easily creating bulk amounts of videos and creating success on YouTube!","longDescription":null,"language":"English","courseUri":"https://www.udemy.com/course/strategic-ways-to-build-your-business-with-youtube/","imageUri":"https://img-b.udemycdn.com/course/750x422/417284_1cf4_6.jpg","duration":"1 total hour","enrolledStudentsCount":"24,898 students","lastUpdated":null,"targetAudiences":["Product/Business Owner","Blog Owner","SEO Beginners","Aspiring Internet Marketers"],"tags":["Business","Sales","YouTube Marketing"],"rating":{"count":120,"averageValue":"4.7"},"instructors":[{"name":"Howard Lynch","url":"/user/howardlynch2/","totalNumberOfStudents":217166,"totalNumberOfReviews":2652,"averageRating":3.9684194595108693},{"name":"Antoine Lelievre","url":"/user/antoinelelievre/","totalNumberOfStudents":209756,"totalNumberOfReviews":2289,"averageRating":3.934247374374999},{"name":"Antoine Jessen","url":"/user/antoine-jessen-2/","totalNumberOfStudents":169193,"totalNumberOfReviews":2085,"averageRating":4.228926125}]},"isAlreadyAFreeCourse":false,"couponData":{"couponCode":"A035A9CD2910BCB65B67","originalPrice":"\u20B9799","discountedPrice":"Free","expirationText":"4 days","discountPercentage":100}},"https://www.udemy.com/course/reality-transmutingpast-the-law-of-attraction-manifesting/":{"courseDetails":{"courseId":4523772,"title":"Reality Transmuting:Past the Law of Attraction \u0026 Manifesting","shortDescription":"Align to your Divine Purpose \u0026 Control Your Reality, Manifesting Your Talents and Generating Abundance in Your Life","longDescription":null,"language":"English","courseUri":"https://www.udemy.com/course/reality-transmutingpast-the-law-of-attraction-manifesting/","imageUri":"https://img-b.udemycdn.com/course/750x422/4523772_6692_7.jpg","duration":"2 total hours","enrolledStudentsCount":"195 students","lastUpdated":null,"targetAudiences":["People who want to Learn Reality Transmuting Principles","People who are Struggling in Life :(","People who have Problems with Relationships","People Who Feel Anxious and Lacking of Somethign Unknown","People who Want to Live an Happy and Fullfilled Life :)","People Who are Already Happy and want to be even Happier :)","People Who Want to Find the Answer to Existential Questions","People Who Want to Create Real Abundance in Life","People Who Want to Find their Purpose in Life"],"tags":["Personal Development","Personal Transformation","Manifestation and Law of Attraction"],"rating":null,"instructors":[{"name":"Gabriele Guarano","url":"/user/gabriele-guarano/","totalNumberOfStudents":2135,"totalNumberOfReviews":0,"averageRating":0}]},"isAlreadyAFreeCourse":false,"couponData":{"couponCode":"FREETRANSMUTING","originalPrice":"\u20B91,699","discountedPrice":"Free","expirationText":"4 days","discountPercentage":100}},"https://www.udemy.com/course/big-data-programming-languages-big-data-vs-data-science/":{"courseDetails":{"courseId":3049106,"title":"Big Data Programming Languages \u0026 Big Data Vs Data Science","shortDescription":"Big Data Programming Languages,Skills to become a Big Data Professional,Differences between Big Data \u0026  Data Science","longDescription":null,"language":"English","courseUri":"https://www.udemy.com/course/big-data-programming-languages-big-data-vs-data-science/","imageUri":"https://img-c.udemycdn.com/course/750x422/3049106_004f_5.jpg","duration":"36 total mins","enrolledStudentsCount":"15,017 students","lastUpdated":null,"targetAudiences":["Beginner level students interested to learn Big Data programming languages"],"tags":["Development","Data Science","Big Data"],"rating":{"count":100,"averageValue":"4.2"},"instructors":[{"name":"Lalitha Audikesavan","url":"/user/lalitha-audikesavan-2/","totalNumberOfStudents":32540,"totalNumberOfReviews":497,"averageRating":3.934962232107023}]},"isAlreadyAFreeCourse":false,"couponData":{"couponCode":"2C31237F57BFFDD360DD","originalPrice":"\u20B92,299","discountedPrice":"Free","expirationText":"4 days","discountPercentage":100}},"https://www.udemy.com/course/java-ile-nesne-merkezli-programlamaya-giris/":{"courseDetails":{"courseId":3659312,"title":"Java ile Nesne-Merkezli Programlamaya Giri\u015F","shortDescription":"Java ve Nesne-Merkezli Programlama\u0027n\u0131n temellerini \u00F6\u011Frenin!","longDescription":null,"language":"T\u00FCrk\u00E7e","courseUri":"https://www.udemy.com/course/java-ile-nesne-merkezli-programlamaya-giris/","imageUri":"https://img-c.udemycdn.com/course/750x422/3659312_a832_4.jpg","duration":"38 total hours","enrolledStudentsCount":"17.807 \u00F6\u011Frenci","lastUpdated":null,"targetAudiences":["Java ile programlama \u00F6\u011Frenmek isteyenler, nesne-merkezli programlama (OOP) \u00F6\u011Frenmek isteyenler, iyi-k\u00F6t\u00FC Java\u0027y\u0131 kullan\u0131p daha etrafl\u0131ca ve do\u011Fru olarak \u00F6\u011Frenmek isteyenler ce Java sertifikalar\u0131n\u0131 almak isteyenler."],"tags":["BT ve Yaz\u0131l\u0131m","Di\u011Fer BT ve Yaz\u0131l\u0131m","Java"],"rating":{"count":968,"averageValue":"4.8"},"instructors":[{"name":"Akin Kaldiroglu","url":"/user/akinkaldiroglu/","totalNumberOfStudents":26760,"totalNumberOfReviews":2635,"averageRating":4.819441433747413}]},"isAlreadyAFreeCourse":false,"couponData":{"couponCode":"AF7D436C49FE7DA47848","originalPrice":"1.499\u00A0\u20B9","discountedPrice":"\u00DCcretsiz","expirationText":"2 g\u00FCn","discountPercentage":100}},"https://www.udemy.com/course/hands-on-sql-servermanagementstudiosql-queriesazurestudio/":{"courseDetails":{"courseId":4205418,"title":"Hands-On SQL Server,ManagementStudio,SQL Queries,AzureStudio","shortDescription":"Detailed Course with Hands-On Practical Lab Sessions-SQL Server,Writing SQL Queries,Management Studio\u0026 Azure Data Studio","longDescription":null,"language":"English","courseUri":"https://www.udemy.com/course/hands-on-sql-servermanagementstudiosql-queriesazurestudio/","imageUri":"https://img-c.udemycdn.com/course/750x422/4205418_287e_2.jpg","duration":"2 total hours","enrolledStudentsCount":"14,011 students","lastUpdated":null,"targetAudiences":["Beginners who are willing to learn SQL Server with Hands-on Practical Demo Sessions","Interested in learning how to Install SQL Server","Those wanted to learn how to use SQL Server Management Studio and Azure Data Studio","Those who want to learn how to store data in database and retrieve data from SQL Server","Those who wanted to start career in SQL Server as there is  high demand for SQL SERVER  DBAs(Database Administrators) \u0026 Developers."],"tags":["IT \u0026 Software","Other IT \u0026 Software","SQL Server"],"rating":{"count":77,"averageValue":"3.9"},"instructors":[{"name":"Lalitha Audikesavan","url":"/user/lalitha-audikesavan-2/","totalNumberOfStudents":32540,"totalNumberOfReviews":497,"averageRating":3.934962232107023}]},"isAlreadyAFreeCourse":false,"couponData":{"couponCode":"8F6E279AEFC4DA3DE8E6","originalPrice":"\u20B93,999","discountedPrice":"Free","expirationText":"4 days","discountPercentage":100}},"https://www.udemy.com/course/practical-cisco-networking-labs/":{"courseDetails":{"courseId":2818343,"title":"Practical Cisco Networking Labs in Cisco Packet Tracer","shortDescription":"Networking concepts explained in a simple way, with many engaging exercises!","longDescription":null,"language":"English","courseUri":"https://www.udemy.com/course/practical-cisco-networking-labs/","imageUri":"https://img-b.udemycdn.com/course/750x422/2818343_f895.jpg","duration":"12 total hours","enrolledStudentsCount":"135,283 students","lastUpdated":null,"targetAudiences":["Networking students"],"tags":["IT \u0026 Software","Network \u0026 Security","Cisco"],"rating":{"count":1456,"averageValue":"4.6"},"instructors":[{"name":"Cyber Quince","url":"/user/cyberquince/","totalNumberOfStudents":280958,"totalNumberOfReviews":4686,"averageRating":4.512504302770083}]},"isAlreadyAFreeCourse":false,"couponData":{"couponCode":"7A222D575018B9AA6669","originalPrice":"\u20B9799","discountedPrice":"Free","expirationText":"4 days","discountPercentage":100}},"https://www.udemy.com/course/how-to-vlog-beginner-to-pro-everything-you-need/":{"courseDetails":{"courseId":4609090,"title":"How to VLOG 2022 : Complete Beginners Course \u002BYouTube","shortDescription":"How to film, edit, come up with ideas, branding, get views and earn fast! I did it, see exactly how I did here","longDescription":null,"language":"English","courseUri":"https://www.udemy.com/course/how-to-vlog-beginner-to-pro-everything-you-need/","imageUri":"https://img-b.udemycdn.com/course/750x422/4609090_fdb1_2.jpg","duration":"5 total hours","enrolledStudentsCount":"7,282 students","lastUpdated":null,"targetAudiences":["Beginner interested in starting a vlog for themselves or a business","Anyone who has considered making a vlog but want to understand how to do it, fil, grow fast, edit and make money"],"tags":["Photography \u0026 Video","Other Photography \u0026 Video","Vlogging"],"rating":{"count":57,"averageValue":"4.7"},"instructors":[{"name":"Dan Britain","url":"/user/daniel-philpott-3/","totalNumberOfStudents":99644,"totalNumberOfReviews":1695,"averageRating":4.622295950898204}]},"isAlreadyAFreeCourse":false,"couponData":{"couponCode":"5E3BB76E69EDE75F6305","originalPrice":"\u20B9799","discountedPrice":"Free","expirationText":"4 days","discountPercentage":100}},"https://www.udemy.com/course/master-python-programming-arabic/":{"courseDetails":{"courseId":3606826,"title":"Master Python Programming (Arabic)","shortDescription":"Start learning programming using Python from scratch to professional","longDescription":null,"language":"Arabic","courseUri":"https://www.udemy.com/course/master-python-programming-arabic/","imageUri":"https://img-c.udemycdn.com/course/750x422/3606826_9200.jpg","duration":"6.5 total hours","enrolledStudentsCount":"136 students","lastUpdated":null,"targetAudiences":["Anyone interested to start learning programming in Python to become a professional and confident programmer"],"tags":["Development","Programming Languages"],"rating":null,"instructors":[{"name":"Ahmed Fahmy","url":"/user/ahmed-fahmy-abdel-hafiz-el-sayed/","totalNumberOfStudents":126,"totalNumberOfReviews":0,"averageRating":0}]},"isAlreadyAFreeCourse":false,"couponData":{"couponCode":"11A98F596F1541D419F7","originalPrice":"\u20B92,799","discountedPrice":"Free","expirationText":"4 days","discountPercentage":100}},"https://www.udemy.com/course/different-technologies-in-big-data/":{"courseDetails":{"courseId":2565910,"title":"Data Analytics,Storage,Mining \u0026 Visual Big Data Technologies","shortDescription":"Data Analytics, Data Storage, Data Mining and Data Visualization Big Data Technologies","longDescription":null,"language":"English","courseUri":"https://www.udemy.com/course/different-technologies-in-big-data/","imageUri":"https://img-c.udemycdn.com/course/750x422/2565910_a62c_3.jpg","duration":"34 total mins","enrolledStudentsCount":"16,036 students","lastUpdated":null,"targetAudiences":["Beginner level interested to learn the different technologies in big data"],"tags":["IT \u0026 Software","Other IT \u0026 Software","Big Data"],"rating":{"count":165,"averageValue":"4.2"},"instructors":[{"name":"Lalitha Audikesavan","url":"/user/lalitha-audikesavan-2/","totalNumberOfStudents":32540,"totalNumberOfReviews":497,"averageRating":3.934962232107023}]},"isAlreadyAFreeCourse":false,"couponData":{"couponCode":"6A1FD25DC9CE10F43D29","originalPrice":"\u20B92,299","discountedPrice":"Free","expirationText":"4 days","discountPercentage":100}},"https://www.udemy.com/course/research-methods-publishing/":{"courseDetails":{"courseId":3272290,"title":"Genetic Algorithms, VAE \u0026 GANs, RBM in DNNs- An Introduction","shortDescription":"Genetic Algorithms, Variational AutoEncoders, RL, Generative Adversarial Networks \u0026 Bayesian Statistics in Deep Learning","longDescription":null,"language":"English","courseUri":"https://www.udemy.com/course/research-methods-publishing/","imageUri":"https://img-c.udemycdn.com/course/750x422/3272290_23e0_5.jpg","duration":"5.5 total hours","enrolledStudentsCount":"6,381 students","lastUpdated":null,"targetAudiences":["Computer science, engineering and research students involved in basic and applied modelling using Algorithms","Beginners who want to keep themselves abreast with leading algorithms"],"tags":["Teaching \u0026 Academics","Other Teaching \u0026 Academics","Research Methods"],"rating":{"count":19,"averageValue":"4.1"},"instructors":[{"name":"Junaid Zafar","url":"/user/junaid-zafar-10/","totalNumberOfStudents":49688,"totalNumberOfReviews":471,"averageRating":3.886079820689655}]},"isAlreadyAFreeCourse":false,"couponData":{"couponCode":"0A18730666A0B8BA04A2","originalPrice":"\u20B94,299","discountedPrice":"Free","expirationText":"1 day","discountPercentage":100}},"https://www.udemy.com/course/digital-marketing-course-in-bangalore-student-edition/":{"courseDetails":{"courseId":2663762,"title":"Futuristic Digital Marketing Course: 2022 Student Edition","shortDescription":"An amazing course focussed on Digital Marketing and futuristic technologies in 2022","longDescription":null,"language":"English","courseUri":"https://www.udemy.com/course/digital-marketing-course-in-bangalore-student-edition/","imageUri":"https://img-c.udemycdn.com/course/750x422/2663762_7169_9.jpg","duration":"1.5 total hours","enrolledStudentsCount":"40,747 students","lastUpdated":null,"targetAudiences":["Anyone who would want to become a digital marketer, promote a business, or know more about building digital marketing strategies.","Anyone who is tired of their day job or wants a career change in the field of digital marketing","People who want to earn an additional income from freelancing","College students in Bangalore who wish to learn digital marketing in the city who are struggling to find a good institute or mentor","Anyone who has the passion and interest to learn new and amazing things about digital marketing and apply artificial intelligence to their daily, tedious marketing tasks"],"tags":["Marketing","Digital Marketing"],"rating":{"count":349,"averageValue":"4.0"},"instructors":[{"name":"Srinidhi Ranganathan","url":"/user/srinidhi-ranganathan/","totalNumberOfStudents":861502,"totalNumberOfReviews":22791,"averageRating":3.966120001291412}]},"isAlreadyAFreeCourse":false,"couponData":{"couponCode":"4B0C89E058920C320CA5","originalPrice":"\u20B9799","discountedPrice":"Free","expirationText":"4 days","discountPercentage":100}},"https://www.udemy.com/course/test-sc-400-microsoft-information-protection-administrator/":{"courseDetails":{"courseId":4728404,"title":"Test SC-400: Microsoft Information Protection Administrator","shortDescription":"Test SC-400: Microsoft Information Protection Administrator -2022","longDescription":null,"language":"Espa\u00F1ol","courseUri":"https://www.udemy.com/course/test-sc-400-microsoft-information-protection-administrator/","imageUri":"https://img-c.udemycdn.com/course/750x422/4728404_2a3d.jpg","duration":"150 questions","enrolledStudentsCount":"1.093 estudiantes","lastUpdated":null,"targetAudiences":["Esta es una audiencia amplia que puede incluir partes interesadas del negocio, profesionales de TI nuevos o existentes, o estudiantes interesados \u200B\u200Ben las soluciones de seguridad, cumplimiento e identidad de Microsoft."],"tags":["Inform\u00E1tica y software","Certificaciones de inform\u00E1tica","Certificaci\u00F3n Microsoft"],"rating":null,"instructors":[{"name":"University Certification","url":"/user/ucert-2/","totalNumberOfStudents":18030,"totalNumberOfReviews":56,"averageRating":4.416197960714285}]},"isAlreadyAFreeCourse":false,"couponData":{"couponCode":"3A83037A52C0A36ED77A","originalPrice":"799\u00A0INR","discountedPrice":"Gratis","expirationText":"4 d\u00EDas","discountPercentage":100}},"https://www.udemy.com/course/sql-desde-cero-curso-practico/":{"courseDetails":{"courseId":1786172,"title":"Consultas en SQL para principiantes","shortDescription":"Ra\u00FAl con m\u00E1s de 5 a\u00F1os de experiencia en An\u00E1lisis de Datos te ense\u00F1ara a hacer consultas en SQL de manera pr\u00E1ctica","longDescription":null,"language":"Spanish","courseUri":"https://www.udemy.com/course/sql-desde-cero-curso-practico/","imageUri":"https://img-c.udemycdn.com/course/750x422/1786172_2c2f_4.jpg","duration":"1 total hour","enrolledStudentsCount":"61,840 students","lastUpdated":null,"targetAudiences":["Est\u00E1 dirigido a quienes dan sus primeros pasos hacia una formaci\u00F3n de Data Analyst (Analista de datos), Data Scientist (Cient\u00EDfico de Datos) o de DBA (Data Base Administrador - Administrador de Bases de Datos)."],"tags":["Development","Database Design \u0026 Development","SQL"],"rating":{"count":2648,"averageValue":"4.4"},"instructors":[{"name":"Ra\u00FAl Montesinos","url":"/user/ralmontesinos/","totalNumberOfStudents":359855,"totalNumberOfReviews":12351,"averageRating":4.377932879640387},{"name":"Numpi Cursos","url":"/user/numpi/","totalNumberOfStudents":350412,"totalNumberOfReviews":27810,"averageRating":4.38381375568727}]},"isAlreadyAFreeCourse":false,"couponData":{"couponCode":"BESTPRICE_JUL2022_2","originalPrice":"\u20B91,999","discountedPrice":"Free","expirationText":"4 days","discountPercentage":100}},"https://www.udemy.com/course/ilgi-cekici-hikayeler-cevirerek-ingilizce-ogreniyoruz-a1-a2/":{"courseDetails":{"courseId":4249006,"title":"\u0130lgi \u00C7ekici Hikayeler \u00C7evirerek \u0130ngilizce \u00D6\u011Freniyoruz A1-A2","shortDescription":"\u0130ngilizce okuma, \u0130ngilizce dinleme, \u0130ngilizce kursu, \u0130ngilizce","longDescription":null,"language":"T\u00FCrk\u00E7e","courseUri":"https://www.udemy.com/course/ilgi-cekici-hikayeler-cevirerek-ingilizce-ogreniyoruz-a1-a2/","imageUri":"https://img-c.udemycdn.com/course/750x422/4249006_c1da.jpg","duration":"17 total hours","enrolledStudentsCount":"4.129 \u00F6\u011Frenci","lastUpdated":null,"targetAudiences":["\u0130ngilizce \u00F6\u011Frenmek isteyenler.","Kli\u015Fe y\u00F6ntemlerden s\u0131k\u0131l\u0131p daha e\u011Flenceli bir \u015Fekilde \u0130ngilizce \u00F6\u011Frenmenin yolunu arayanlar."],"tags":["\u00D6\u011Fretim ve Akademi","Dil \u00D6\u011Frenimi","\u0130ngilizce"],"rating":{"count":215,"averageValue":"4.5"},"instructors":[{"name":"Abdurrahman TEKIN","url":"/user/abdurrahman-tekin/","totalNumberOfStudents":19811,"totalNumberOfReviews":1098,"averageRating":4.719062261916462}]},"isAlreadyAFreeCourse":false,"couponData":{"couponCode":"89FA7AA32EA5699E9EAB","originalPrice":"1.299\u00A0\u20B9","discountedPrice":"\u00DCcretsiz","expirationText":"23 saat","discountPercentage":100}},"https://www.udemy.com/course/viralnomics-creating-youtube-video-ideas-that-go-viral/":{"courseDetails":{"courseId":972262,"title":"Viral YouTube Marketing - Crash Course \u002B Live Class","shortDescription":"The Ultimate Viral YouTube Marketing Course to learn and master in 2022.","longDescription":null,"language":"English","courseUri":"https://www.udemy.com/course/viralnomics-creating-youtube-video-ideas-that-go-viral/","imageUri":"https://img-c.udemycdn.com/course/750x422/972262_d236_4.jpg","duration":"2.5 total hours","enrolledStudentsCount":"127,021 students","lastUpdated":null,"targetAudiences":["People of any age or ability","People from any country who love YouTube","People with an interest in YouTube or YouTube video creation","Young entrepreneurs who are hard-core YouTube viewers","Internet marketers who are YouTube addicts.","Udemy\u00A0teachers who can create great courses on any topic on \u201CYouTube\u201D","Professionals who use YouTube for marketing","Video creators who upload regularly YouTube videos to YouTube","Video marketing lovers who wish to take their brand on YouTube to the next level with implementing new-age SEO secrets."],"tags":["Marketing","Video \u0026 Mobile Marketing","Viral Marketing"],"rating":{"count":1257,"averageValue":"4.2"},"instructors":[{"name":"Srinidhi Ranganathan","url":"/user/srinidhi-ranganathan/","totalNumberOfStudents":861502,"totalNumberOfReviews":22791,"averageRating":3.966120001291412},{"name":"First Look Digital Marketing Solutions Pvt. Ltd.","url":"/user/firstlookai/","totalNumberOfStudents":579570,"totalNumberOfReviews":9875,"averageRating":4.07377115934195}]},"isAlreadyAFreeCourse":false,"couponData":{"couponCode":"C00E5FC0984E8D14D0A3","originalPrice":"\u20B9799","discountedPrice":"Free","expirationText":"4 days","discountPercentage":100}},"https://www.udemy.com/course/simulador-156-11577-check-point-certified-security-master/":{"courseDetails":{"courseId":4749030,"title":"Simulador 156-115.77 Check Point Certified Security Master","shortDescription":"Simulador 156-115.77 Check Point Certified Security Master","longDescription":null,"language":"Espa\u00F1ol","courseUri":"https://www.udemy.com/course/simulador-156-11577-check-point-certified-security-master/","imageUri":"https://img-c.udemycdn.com/course/750x422/4749030_ff12.jpg","duration":"308 questions","enrolledStudentsCount":"1.165 estudiantes","lastUpdated":null,"targetAudiences":["Anyone who want to do practice and exam preparation for the CCSM 156-115.77 Check Point Certification Exam"],"tags":["Inform\u00E1tica y software","Certificaciones de inform\u00E1tica","Certificaci\u00F3n de Check Point"],"rating":null,"instructors":[{"name":"U Class","url":"/user/alberto-acosta-ruiz/","totalNumberOfStudents":14807,"totalNumberOfReviews":62,"averageRating":4.529196625806453}]},"isAlreadyAFreeCourse":false,"couponData":{"couponCode":"1C946044BD301EC3B86D","originalPrice":"799\u00A0INR","discountedPrice":"Gratis","expirationText":"4 d\u00EDas","discountPercentage":100}},"https://www.udemy.com/course/ileri-bilgisayar-isletmenligi-kursu-2021-sertifikal/":{"courseDetails":{"courseId":4395856,"title":"\u0130leri Bilgisayar \u0130\u015Fletmenli\u011Fi Kursu | 2022 | Sertifikal\u0131","shortDescription":"Bilgisayar \u0130\u015Fletmenli\u011Fi Kursu  Sertifika Program\u0131","longDescription":null,"language":"T\u00FCrk\u00E7e","courseUri":"https://www.udemy.com/course/ileri-bilgisayar-isletmenligi-kursu-2021-sertifikal/","imageUri":"https://img-c.udemycdn.com/course/750x422/4395856_4d47.jpg","duration":"20.5 total hours","enrolledStudentsCount":"1.243 \u00F6\u011Frenci","lastUpdated":null,"targetAudiences":["B\u00FCro Memular\u0131na","\u00D6\u011Fretmenlere","Bili\u015Fim D\u00FCnyas\u0131na Girmeyi Planlayan Herkese","Bilgisayar Bilgisi Edinmek \u0130steyenlere"],"tags":["BT ve Yaz\u0131l\u0131m","BT Sertifikalar\u0131","Bilgisayar Kullan\u0131m\u0131n\u0131n Temelleri"],"rating":{"count":36,"averageValue":"4.6"},"instructors":[{"name":"Tuncay EROL","url":"/user/tuncay-erol/","totalNumberOfStudents":17741,"totalNumberOfReviews":832,"averageRating":4.82996107844523}]},"isAlreadyAFreeCourse":false,"couponData":{"couponCode":"4DFA8A30A9D93E9DFA9F","originalPrice":"799\u00A0\u20B9","discountedPrice":"\u00DCcretsiz","expirationText":"4 g\u00FCn","discountPercentage":100}},"https://www.udemy.com/course/the-youtube-academy-speed-growth-plan-proven-results-2022/":{"courseDetails":{"courseId":4487028,"title":"How To Grow Your YouTube Channel Fast in 2022! Step-by-Step","shortDescription":"Grow Fast on YouTube The Tried \u0026 Tested Method! Beat the Algorithm, See My Analytics, Here\u0027s How I Did It...","longDescription":null,"language":"English","courseUri":"https://www.udemy.com/course/the-youtube-academy-speed-growth-plan-proven-results-2022/","imageUri":"https://img-b.udemycdn.com/course/750x422/4487028_7c9e_2.jpg","duration":"5 total hours","enrolledStudentsCount":"12,711 students","lastUpdated":null,"targetAudiences":["Beginner Youtube creators","All aspiring Youtube creators","Existing YouTube channel owners who want to grow faster"],"tags":["Marketing","Growth Hacking","YouTube Audience Growth"],"rating":{"count":195,"averageValue":"4.6"},"instructors":[{"name":"Dan Britain","url":"/user/daniel-philpott-3/","totalNumberOfStudents":99644,"totalNumberOfReviews":1695,"averageRating":4.622295950898204}]},"isAlreadyAFreeCourse":false,"couponData":{"couponCode":"AED10E5F7129635AAD94","originalPrice":"\u20B9799","discountedPrice":"Free","expirationText":"4 days","discountPercentage":100}},"https://www.udemy.com/course/the-ultimate-text-to-video-creation-course/":{"courseDetails":{"courseId":2926660,"title":"The Ultimate Text-To-Video Creation Course (2022 Edition)","shortDescription":"An incredible online course focussed on text-to-video creation tools in 2022","longDescription":null,"language":"English","courseUri":"https://www.udemy.com/course/the-ultimate-text-to-video-creation-course/","imageUri":"https://img-c.udemycdn.com/course/750x422/2926660_220e_6.jpg","duration":"1 total hour","enrolledStudentsCount":"38,502 students","lastUpdated":null,"targetAudiences":["Video specialists, marketers, social media executives and anyone who is looking to convert text to videos to promote their brand","Anyone who is looking to learn the secretive automation techniques in Text-To-Video Creation in 2022","Bloggers who want to create audio blogs and even video blogs - quick and easy","Anyone who is interested to learn new and exciting concepts in text-to-video-creation"],"tags":["Marketing","Digital Marketing","Video Creation"],"rating":{"count":323,"averageValue":"3.8"},"instructors":[{"name":"Srinidhi Ranganathan","url":"/user/srinidhi-ranganathan/","totalNumberOfStudents":861502,"totalNumberOfReviews":22791,"averageRating":3.966120001291412},{"name":"Saranya Srinidhi","url":"/user/saranya-srinidhi/","totalNumberOfStudents":688607,"totalNumberOfReviews":9034,"averageRating":3.925023621077958}]},"isAlreadyAFreeCourse":false,"couponData":{"couponCode":"6E0BB26468C77458986B","originalPrice":"\u20B91,299","discountedPrice":"Free","expirationText":"4 days","discountPercentage":100}},"https://www.udemy.com/course/el-curso-completo-de-google-sheets-desde-cero/":{"courseDetails":{"courseId":3694482,"title":"Google Spreadsheets: Empieza desde cero","shortDescription":"La mejor alternativa a Microsoft Excel. Domina las hojas de c\u00E1lculo de Google.","longDescription":null,"language":"Spanish","courseUri":"https://www.udemy.com/course/el-curso-completo-de-google-sheets-desde-cero/","imageUri":"https://img-c.udemycdn.com/course/750x422/3694482_eed8_14.jpg","duration":"1.5 total hours","enrolledStudentsCount":"54,655 students","lastUpdated":null,"targetAudiences":["Estudiantes, profesionistas y emprendedores que quieran aprender a usar herramientas en la nube.","Estudiantes, profesionistas y emprendedores que requieran una herramienta para trabajar con datos de forma gratuita.","Estudiantes, profesionistas y emprendedores que quieran aprender a trabajar con datos con herramientas en la nube."],"tags":["Office Productivity","Google","Google Sheets"],"rating":{"count":564,"averageValue":"4.4"},"instructors":[{"name":"Ra\u00FAl Montesinos","url":"/user/ralmontesinos/","totalNumberOfStudents":359855,"totalNumberOfReviews":12351,"averageRating":4.377932879640387},{"name":"Numpi Cursos","url":"/user/numpi/","totalNumberOfStudents":350412,"totalNumberOfReviews":27810,"averageRating":4.38381375568727}]},"isAlreadyAFreeCourse":false,"couponData":{"couponCode":"BESTPRICE_JUL2022_2","originalPrice":"\u20B9799","discountedPrice":"Free","expirationText":"4 days","discountPercentage":100}},"https://www.udemy.com/course/aprende-sql-desde-cero-curso-con-mas-de-50-ejercicios/":{"courseDetails":{"courseId":2040612,"title":"Aprende SQL desde cero: \u00A1Curso con mas de 50 ejercicios! 1","shortDescription":"Un curso integral donde aprender\u00E1s como hacer consultas SQL complejas.","longDescription":null,"language":"Spanish","courseUri":"https://www.udemy.com/course/aprende-sql-desde-cero-curso-con-mas-de-50-ejercicios/","imageUri":"https://img-c.udemycdn.com/course/750x422/2040612_6147_12.jpg","duration":"1.5 total hours","enrolledStudentsCount":"84,829 students","lastUpdated":null,"targetAudiences":["Cualquier persona interesada en aprender m\u00E1s sobre SQL o an\u00E1lisis de datos."],"tags":["Development","Database Design \u0026 Development","SQL"],"rating":{"count":2427,"averageValue":"4.4"},"instructors":[{"name":"Ra\u00FAl Montesinos","url":"/user/ralmontesinos/","totalNumberOfStudents":359855,"totalNumberOfReviews":12351,"averageRating":4.377932879640387},{"name":"Numpi Cursos","url":"/user/numpi/","totalNumberOfStudents":350412,"totalNumberOfReviews":27810,"averageRating":4.38381375568727}]},"isAlreadyAFreeCourse":false,"couponData":{"couponCode":"BESTPRICE_JUL2022_2","originalPrice":"\u20B9799","discountedPrice":"Free","expirationText":"4 days","discountPercentage":100}},"https://www.udemy.com/course/artificial-intelligence-video-creation-amazing-video-tools/":{"courseDetails":{"courseId":1298012,"title":"Artificial Intelligence in Video Creation: Supreme Edition","shortDescription":"Learn the secretive tools and technologies in 2022 covered as part of Artificial Intelligence (AI) in Video Creation","longDescription":null,"language":"English","courseUri":"https://www.udemy.com/course/artificial-intelligence-video-creation-amazing-video-tools/","imageUri":"https://img-c.udemycdn.com/course/750x422/1298012_b1cf_6.jpg","duration":"2.5 total hours","enrolledStudentsCount":"99,214 students","lastUpdated":null,"targetAudiences":["Video creators, Marketers, Social Media Specialists and anyone who is looking to create videos to promote their brand or business.","Anyone who is looking to learn the artificial intelligence and automation techniques in Video Creation in 2022","Passionate students who want to master the concept of Artificial Intelligence (AI) in Video Creation."],"tags":["Design","Other Design","Video Creation"],"rating":{"count":610,"averageValue":"4.4"},"instructors":[{"name":"Srinidhi Ranganathan","url":"/user/srinidhi-ranganathan/","totalNumberOfStudents":861502,"totalNumberOfReviews":22791,"averageRating":3.966120001291412},{"name":"First Look Digital Marketing Solutions Pvt. Ltd.","url":"/user/firstlookai/","totalNumberOfStudents":579570,"totalNumberOfReviews":9875,"averageRating":4.07377115934195}]},"isAlreadyAFreeCourse":false,"couponData":{"couponCode":"0E8D8E4539A6F51D0FA5","originalPrice":"\u20B9799","discountedPrice":"Free","expirationText":"4 days","discountPercentage":100}},"https://www.udemy.com/course/digital-voice-cloning-using-artificial-intelligence-ai/":{"courseDetails":{"courseId":2636128,"title":"Digital Voice Cloning using Artificial Intelligence in 2022","shortDescription":"A game-changing course focussed on Artificial Intelligence (AI) Powered Digital Voice Cloning","longDescription":null,"language":"English","courseUri":"https://www.udemy.com/course/digital-voice-cloning-using-artificial-intelligence-ai/","imageUri":"https://img-c.udemycdn.com/course/750x422/2636128_8103_6.jpg","duration":"1 total hour","enrolledStudentsCount":"21,388 students","lastUpdated":null,"targetAudiences":["Enterpreneurs who want to build a big audio content library in the fastest way possible","Bloggers and Podcast makers who would like to convert their text to audio through AI Voice cloning tools","Digital Marketers who wish to create a lot of audio content with the power of AI Voice cloning tools","Video production studio experts who wish to clone their voice to include in their future projects","Passionate individuals who are interested to learn voice-cloning technology for their research purposes","Students who wish to witness the next revolution in audio technology"],"tags":["IT \u0026 Software","Other IT \u0026 Software","Artificial Intelligence"],"rating":{"count":135,"averageValue":"2.8"},"instructors":[{"name":"Srinidhi Ranganathan","url":"/user/srinidhi-ranganathan/","totalNumberOfStudents":861502,"totalNumberOfReviews":22791,"averageRating":3.966120001291412},{"name":"Saranya Srinidhi","url":"/user/saranya-srinidhi/","totalNumberOfStudents":688607,"totalNumberOfReviews":9034,"averageRating":3.925023621077958}]},"isAlreadyAFreeCourse":false,"couponData":{"couponCode":"8D71EDF1DD71F871A3D6","originalPrice":"\u20B91,299","discountedPrice":"Free","expirationText":"4 days","discountPercentage":100}},"https://www.udemy.com/course/microsoft-excel-de-cero-a-analista-de-datos-en-power-bi/":{"courseDetails":{"courseId":4270096,"title":"Microsoft Excel: De cero a analista de datos en Power BI","shortDescription":"El curso te dar\u00E1 un dominio completo de Microsoft Excel y te introducir\u00E1 a la inteligencia de negocio.","longDescription":null,"language":"Spanish","courseUri":"https://www.udemy.com/course/microsoft-excel-de-cero-a-analista-de-datos-en-power-bi/","imageUri":"https://img-c.udemycdn.com/course/750x422/4270096_4f89_9.jpg","duration":"6 total hours","enrolledStudentsCount":"34,555 students","lastUpdated":null,"targetAudiences":["Toda persona que necesite aprender y/o dominar Microsoft Excel ya sea de forma educativa o profesional.","Profesionistas que necesiten mejorar sus productividad en la oficina.","Profesionistas que requieran trabajar con una gran cantidad de datos."],"tags":["Business","Business Analytics \u0026 Intelligence","Excel VBA"],"rating":{"count":560,"averageValue":"4.3"},"instructors":[{"name":"Numpi Cursos","url":"/user/numpi/","totalNumberOfStudents":350412,"totalNumberOfReviews":27810,"averageRating":4.38381375568727},{"name":"Hugo Aguilar Svonik","url":"/user/hugo-aguilar-svonik/","totalNumberOfStudents":37015,"totalNumberOfReviews":628,"averageRating":4.408043847058823}]},"isAlreadyAFreeCourse":false,"couponData":{"couponCode":"BESTPRICE_JUL2022_2","originalPrice":"\u20B93,899","discountedPrice":"Free","expirationText":"4 days","discountPercentage":100}},"https://www.udemy.com/course/python-3-plus-python-desde-cero-data-analysis-y-matplot/":{"courseDetails":{"courseId":3756288,"title":"Python 3 Plus: Python desde Cero \u002B Data Analysis y Matplot","shortDescription":"El curso que te da m\u00E1s valor 2021: Aprende Python 3 desde cero hasta experto en Data Analysis.","longDescription":null,"language":"Spanish","courseUri":"https://www.udemy.com/course/python-3-plus-python-desde-cero-data-analysis-y-matplot/","imageUri":"https://img-c.udemycdn.com/course/750x422/3756288_497d_19.jpg","duration":"14.5 total hours","enrolledStudentsCount":"91,978 students","lastUpdated":null,"targetAudiences":["Profesionistas que quieran aprender a programar en Python para facilitar sus tareas del d\u00EDa a d\u00EDa.","Desarrolladores que quieran aprender Python de una manera \u00E1gil, completa y sencilla.","Profesionistas que requieran trabajar con una gran cantidad de datos.","Profesionistas que necesiten analizar grandes vol\u00FAmenes de datos."],"tags":["Development","Programming Languages","Python"],"rating":{"count":1396,"averageValue":"4.4"},"instructors":[{"name":"Numpi Cursos","url":"/user/numpi/","totalNumberOfStudents":350412,"totalNumberOfReviews":27810,"averageRating":4.38381375568727}]},"isAlreadyAFreeCourse":false,"couponData":{"couponCode":"BESTPRICE_JUL2022_2","originalPrice":"\u20B93,899","discountedPrice":"Free","expirationText":"4 days","discountPercentage":100}},"https://www.udemy.com/course/microsoft-excel-intermedio/":{"courseDetails":{"courseId":3593486,"title":"Microsoft Excel: Intermedio, Funciones, Tablas Din\u00E1micas y \u002B","shortDescription":"Aumenta tu productividad y amplia tus herramientas de an\u00E1lisis","longDescription":null,"language":"Spanish","courseUri":"https://www.udemy.com/course/microsoft-excel-intermedio/","imageUri":"https://img-c.udemycdn.com/course/750x422/3593486_2487_17.jpg","duration":"2 total hours","enrolledStudentsCount":"72,327 students","lastUpdated":null,"targetAudiences":["Profesionales que quieran dominar excel.","Profesionales que quieran realizar sus tareas m\u00E1s eficientemente.","Profesionales que necesiten el manejo de Excel para cuestiones laborales."],"tags":["Office Productivity","Microsoft","Excel"],"rating":{"count":1630,"averageValue":"4.5"},"instructors":[{"name":"Numpi Cursos","url":"/user/numpi/","totalNumberOfStudents":350412,"totalNumberOfReviews":27810,"averageRating":4.38381375568727}]},"isAlreadyAFreeCourse":false,"couponData":{"couponCode":"BESTPRICE_JUL2022_2","originalPrice":"\u20B93,899","discountedPrice":"Free","expirationText":"4 days","discountPercentage":100}},"https://www.udemy.com/course/curso-python-desde-cero/":{"courseDetails":{"courseId":3754012,"title":"Escuela de Python 2021: Aprende Python 3.9\u002B de cero a Master","shortDescription":"Curso de Python 2021 : Aprende Python con Flask, Django, Web Scraping, Data Science y MySQL,HTML, CSS, Bootstrap","longDescription":null,"language":"Espa\u00F1ol","courseUri":"https://www.udemy.com/course/curso-python-desde-cero/","imageUri":"https://img-c.udemycdn.com/course/750x422/3754012_2862_7.jpg","duration":"21 total hours","enrolledStudentsCount":"13.030 estudiantes","lastUpdated":null,"targetAudiences":["Para todos los nuevos en programaci\u00F3n","Para todo los nuevos en Python"],"tags":["Desarrollo","Lenguajes de programaci\u00F3n","Python"],"rating":{"count":225,"averageValue":"4.7"},"instructors":[{"name":"Roel Code","url":"/user/alex-roel/","totalNumberOfStudents":106271,"totalNumberOfReviews":4162,"averageRating":4.515905187690632}]},"isAlreadyAFreeCourse":false,"couponData":{"couponCode":"DCA994843919","originalPrice":"799\u00A0INR","discountedPrice":"Gratis","expirationText":"4 d\u00EDas","discountPercentage":100}},"https://www.udemy.com/course/sql-creacion-de-bd/":{"courseDetails":{"courseId":3456530,"title":"SQL: Creaci\u00F3n de Bases de Datos (De cero a profesional)","shortDescription":"Aprende a dise\u00F1ar bases de datos eficientes para posteriormente crearlas, modificarlas y manipularlas en SQL.","longDescription":null,"language":"Spanish","courseUri":"https://www.udemy.com/course/sql-creacion-de-bd/","imageUri":"https://img-c.udemycdn.com/course/750x422/3456530_2d96_12.jpg","duration":"2 total hours","enrolledStudentsCount":"96,839 students","lastUpdated":null,"targetAudiences":["Desarrolladores","Financieros","Cient\u00EDficos de Datos","Analistas de Datos","Analistas","Oficinistas","Ejecutivos Comerciales","Emprendedores"],"tags":["Development","Database Design \u0026 Development","SQL"],"rating":{"count":2481,"averageValue":"4.1"},"instructors":[{"name":"Numpi Cursos","url":"/user/numpi/","totalNumberOfStudents":350412,"totalNumberOfReviews":27810,"averageRating":4.38381375568727}]},"isAlreadyAFreeCourse":false,"couponData":{"couponCode":"BESTPRICE_JUL2022_2","originalPrice":"\u20B9799","discountedPrice":"Free","expirationText":"4 days","discountPercentage":100}},"https://www.udemy.com/course/webinar-crusher-by-howard-lynch-sell-high-ticket-products/":{"courseDetails":{"courseId":845330,"title":"Webinar Mastery - Sell High Ticket Products!","shortDescription":"Your complete guide to selling through webinars, and how to make sure they are packed every time. Everything is included","longDescription":null,"language":"English","courseUri":"https://www.udemy.com/course/webinar-crusher-by-howard-lynch-sell-high-ticket-products/","imageUri":"https://img-b.udemycdn.com/course/750x422/845330_b60b_2.jpg","duration":"2 total hours","enrolledStudentsCount":"21,778 students","lastUpdated":null,"targetAudiences":["Affiliate Marketers"],"tags":["Business","Sales","Sales Skills"],"rating":{"count":28,"averageValue":"4.6"},"instructors":[{"name":"Howard Lynch","url":"/user/howardlynch2/","totalNumberOfStudents":217166,"totalNumberOfReviews":2652,"averageRating":3.9684194595108693},{"name":"Antoine Lelievre","url":"/user/antoinelelievre/","totalNumberOfStudents":209756,"totalNumberOfReviews":2289,"averageRating":3.934247374374999},{"name":"Antoine Jessen","url":"/user/antoine-jessen-2/","totalNumberOfStudents":169193,"totalNumberOfReviews":2085,"averageRating":4.228926125}]},"isAlreadyAFreeCourse":false,"couponData":{"couponCode":"BEC85122BD6CDA05839A","originalPrice":"\u20B9799","discountedPrice":"Free","expirationText":"4 days","discountPercentage":100}},"https://www.udemy.com/course/powersystemopt/":{"courseDetails":{"courseId":1797284,"title":"Mastering Energy and Power System Optimization in GAMS","shortDescription":"Online guide on how to learn GAMS like a Pro.  Complete Practical Examples, take your GAMS skills to the next level now!","longDescription":null,"language":"English","courseUri":"https://www.udemy.com/course/powersystemopt/","imageUri":"https://img-c.udemycdn.com/course/750x422/1797284_d85d_7.jpg","duration":"5.5 total hours","enrolledStudentsCount":"27,501 students","lastUpdated":null,"targetAudiences":["Anyone who needs to make some sort of decisions","Any discipline that requires optimization and decision making","Power system academics or industry experts","Beginner students in power system operation and planning","PhD/MSc students in power system operation and planning","PhD/MSc students in energy systems","Power system utility R\u0026D staffs","Entrepreneurs","Business Owners involved in Energy industry"],"tags":["Teaching \u0026 Academics","Engineering","Electrical Engineering"],"rating":{"count":723,"averageValue":"4.9"},"instructors":[{"name":"Optimization Team","url":"/user/alireza-soroudi/","totalNumberOfStudents":91766,"totalNumberOfReviews":1603,"averageRating":4.7743411063909775}]},"isAlreadyAFreeCourse":false,"couponData":{"couponCode":"97D7A5800BA182AA9F99","originalPrice":"\u20B97,900","discountedPrice":"Free","expirationText":"4 days","discountPercentage":100}},"https://www.udemy.com/course/learn-big-data-basics/":{"courseDetails":{"courseId":2544537,"title":"Learn Big Data Basics","shortDescription":"Big Data Concepts,History \u0026 Jobs in Big Data,Types,Characteristics,Categories,Frameworks,Programming languages,Paradigms","longDescription":null,"language":"English","courseUri":"https://www.udemy.com/course/learn-big-data-basics/","imageUri":"https://img-c.udemycdn.com/course/750x422/2544537_11ac_7.jpg","duration":"44 total mins","enrolledStudentsCount":"17,013 students","lastUpdated":null,"targetAudiences":["This course is for students at beginner level interested to learn big data basics","For those who want to start a new career in big data field"],"tags":["IT \u0026 Software","Other IT \u0026 Software","Big Data"],"rating":{"count":155,"averageValue":"3.5"},"instructors":[{"name":"Lalitha Audikesavan","url":"/user/lalitha-audikesavan-2/","totalNumberOfStudents":32540,"totalNumberOfReviews":497,"averageRating":3.934962232107023}]},"isAlreadyAFreeCourse":false,"couponData":{"couponCode":"C5074947DBB71ABF3633","originalPrice":"\u20B92,299","discountedPrice":"Free","expirationText":"4 days","discountPercentage":100}},"https://www.udemy.com/course/tableau-10-desde-cero/":{"courseDetails":{"courseId":2288849,"title":"Tableau: Empieza desde cero","shortDescription":"Entra al mundo del business intelligence y aprende a visualizar grandes cantidades de informaci\u00F3n.","longDescription":null,"language":"Spanish","courseUri":"https://www.udemy.com/course/tableau-10-desde-cero/","imageUri":"https://img-c.udemycdn.com/course/750x422/2288849_5725_9.jpg","duration":"1.5 total hours","enrolledStudentsCount":"54,310 students","lastUpdated":null,"targetAudiences":["Deber\u00EDa tomar este curso si desea aprender Tableau completamente desde cero.","Deber\u00EDas tomar este curso si conoces algunas habilidades de Tableau pero quieres mejorar.","Debe tomar este curso si es bueno con Tableau y desea llevar sus habilidades al siguiente nivel y realmente aprovechar todo el potencial de Tableau."],"tags":["Business","Business Analytics \u0026 Intelligence","Tableau"],"rating":{"count":572,"averageValue":"4.3"},"instructors":[{"name":"Ra\u00FAl Montesinos","url":"/user/ralmontesinos/","totalNumberOfStudents":359855,"totalNumberOfReviews":12351,"averageRating":4.377932879640387},{"name":"Numpi Cursos","url":"/user/numpi/","totalNumberOfStudents":350412,"totalNumberOfReviews":27810,"averageRating":4.38381375568727}]},"isAlreadyAFreeCourse":false,"couponData":{"couponCode":"BESTPRICE_JUL2022_2","originalPrice":"\u20B9799","discountedPrice":"Free","expirationText":"4 days","discountPercentage":100}},"https://www.udemy.com/course/artificial-intelligence-music-creation-remixing-2018/":{"courseDetails":{"courseId":1724702,"title":"Artificial Intelligence Music Creation (2022 New Edition)","shortDescription":"Learn the most amazing Artificial Intelligence (AI) Powered Music Creation Tools","longDescription":null,"language":"English","courseUri":"https://www.udemy.com/course/artificial-intelligence-music-creation-remixing-2018/","imageUri":"https://img-c.udemycdn.com/course/750x422/1724702_eee4_7.jpg","duration":"1 total hour","enrolledStudentsCount":"44,468 students","lastUpdated":null,"targetAudiences":["This course is a must for professionals who are in the music industry who want to use Artificial Intelligence (AI) technology for music composition","This course is for anyone who is passionate about learning music and looking to create the same with Artificial Intelligence Technology","This course is for anyone who is looking to upload unique and new music created with artificial intelligence technology on video platforms like YouTube for earnings"],"tags":["Development","Data Science","Artificial Intelligence"],"rating":{"count":255,"averageValue":"4.5"},"instructors":[{"name":"Srinidhi Ranganathan","url":"/user/srinidhi-ranganathan/","totalNumberOfStudents":861502,"totalNumberOfReviews":22791,"averageRating":3.966120001291412}]},"isAlreadyAFreeCourse":false,"couponData":{"couponCode":"7A03C4F8B47018AE387D","originalPrice":"\u20B91,299","discountedPrice":"Free","expirationText":"4 days","discountPercentage":100}},"https://www.udemy.com/course/power-bi-2021-proyectos-reales-para-volverte-un-master/":{"courseDetails":{"courseId":4004864,"title":"Power BI: 8 Proyectos reales para volverte un master","shortDescription":"Vu\u00E9lvete un experto del Business Intelligence y extrae valor de los datos","longDescription":null,"language":"Spanish","courseUri":"https://www.udemy.com/course/power-bi-2021-proyectos-reales-para-volverte-un-master/","imageUri":"https://img-c.udemycdn.com/course/750x422/4004864_c2d2_18.jpg","duration":"4 total hours","enrolledStudentsCount":"62,280 students","lastUpdated":null,"targetAudiences":["Estudiantes y profesionales que quieran entrar en el mundo de los datos y el Business Intelligence.","Estudiantes y profesionales que quieran aprender a utilizar Power BI."],"tags":["Business","Business Analytics \u0026 Intelligence","Microsoft Power BI"],"rating":{"count":666,"averageValue":"4.2"},"instructors":[{"name":"Numpi Cursos","url":"/user/numpi/","totalNumberOfStudents":350412,"totalNumberOfReviews":27810,"averageRating":4.38381375568727}]},"isAlreadyAFreeCourse":false,"couponData":{"couponCode":"BESTPRICE_JUL2022_2","originalPrice":"\u20B93,899","discountedPrice":"Free","expirationText":"4 days","discountPercentage":100}},"https://www.udemy.com/course/data-analysis-con-sql-y-tableau/":{"courseDetails":{"courseId":4025408,"title":"Microsoft SQL Server: An\u00E1lisis de datos con Tableau","shortDescription":"Mejora tus habilidades anal\u00EDticas comerciales con SQL y visualizaci\u00F3n de datos","longDescription":null,"language":"Spanish","courseUri":"https://www.udemy.com/course/data-analysis-con-sql-y-tableau/","imageUri":"https://img-c.udemycdn.com/course/750x422/4025408_2095_14.jpg","duration":"2 total hours","enrolledStudentsCount":"64,906 students","lastUpdated":null,"targetAudiences":["Estudiantes y profesionales que quieran entrar en el mundo de los datos y el Business Intelligence."],"tags":["Business","Business Analytics \u0026 Intelligence","Data Analysis"],"rating":{"count":515,"averageValue":"4.3"},"instructors":[{"name":"Numpi Cursos","url":"/user/numpi/","totalNumberOfStudents":350412,"totalNumberOfReviews":27810,"averageRating":4.38381375568727},{"name":"Ra\u00FAl Montesinos","url":"/user/ralmontesinos/","totalNumberOfStudents":359855,"totalNumberOfReviews":12351,"averageRating":4.377932879640387}]},"isAlreadyAFreeCourse":false,"couponData":{"couponCode":"BESTPRICE_JUL2022_2","originalPrice":"\u20B93,899","discountedPrice":"Free","expirationText":"4 days","discountPercentage":100}},"https://www.udemy.com/course/mongodb-aprende-desde-cero/":{"courseDetails":{"courseId":4110700,"title":"MongoDB: Aprende desde cero a experto","shortDescription":"Vuelvete un experto en Bases de Datos no relacionales aprendiendo de una manera f\u00E1cil y sencilla.","longDescription":null,"language":"Spanish","courseUri":"https://www.udemy.com/course/mongodb-aprende-desde-cero/","imageUri":"https://img-c.udemycdn.com/course/750x422/4110700_b686_17.jpg","duration":"7.5 total hours","enrolledStudentsCount":"77,836 students","lastUpdated":null,"targetAudiences":["Personas que quieran dominar las bases de datos NoSQL con MongoDB.","Personas que quieran iniciarse en el mundo del Big Data y el Data Science.","Personas que quieran expandir sus conocimientos acerca de las bases de datos."],"tags":["Development","Database Design \u0026 Development","MongoDB"],"rating":{"count":782,"averageValue":"4.4"},"instructors":[{"name":"Numpi Cursos","url":"/user/numpi/","totalNumberOfStudents":350412,"totalNumberOfReviews":27810,"averageRating":4.38381375568727}]},"isAlreadyAFreeCourse":false,"couponData":{"couponCode":"BESTPRICE_JUL2022_2","originalPrice":"\u20B93,899","discountedPrice":"Free","expirationText":"4 days","discountPercentage":100}},"https://www.udemy.com/course/roboauthor-content-writing-automation-2019-part-1/":{"courseDetails":{"courseId":2496302,"title":"RoboAuthor: Content Writing Automation - Part 1 \u002B Live Class","shortDescription":"Command Robots to write stories, scripts or poetry in any author\u0027s style in minutes with Artificial Intelligence in 2022","longDescription":null,"language":"English","courseUri":"https://www.udemy.com/course/roboauthor-content-writing-automation-2019-part-1/","imageUri":"https://img-c.udemycdn.com/course/750x422/2496302_e9fe_6.jpg","duration":"1.5 total hours","enrolledStudentsCount":"62,341 students","lastUpdated":null,"targetAudiences":["Content creators who want to ditch the manual process of writing business content and want to shift to AI-Robots written content and speed up the process in order for growth-hacking.","Digital Marketers who wish to use inbound content marketing and the use of robo-written e-books for promotional use to market their business easier.","Authors who wish to use artificial intelligence technology to aid them in the writing process and to finish writing books in hours - instead of spending sleepless nights thinking of ideas on what to write and how to fill the content blocks.","Anyone who has a desire to learn Artificial Intelligence (AI) powered content writing tech tools."],"tags":["Teaching \u0026 Academics","Other Teaching \u0026 Academics","AI Content Generation"],"rating":{"count":427,"averageValue":"4.7"},"instructors":[{"name":"Srinidhi Ranganathan","url":"/user/srinidhi-ranganathan/","totalNumberOfStudents":861502,"totalNumberOfReviews":22791,"averageRating":3.966120001291412}]},"isAlreadyAFreeCourse":false,"couponData":{"couponCode":"42AE9880F0649BB26658","originalPrice":"\u20B9799","discountedPrice":"Free","expirationText":"1 day","discountPercentage":100}},"https://www.udemy.com/course/the-art-of-business-branding-storytelling/":{"courseDetails":{"courseId":3743958,"title":"The Art of Business Brand Storytelling","shortDescription":"Create Brand Storytelling Advertising Strategy To Build Emotional Connection With Your Customer","longDescription":null,"language":"English","courseUri":"https://www.udemy.com/course/the-art-of-business-branding-storytelling/","imageUri":"https://img-c.udemycdn.com/course/750x422/3743958_0d79_5.jpg","duration":"4 total hours","enrolledStudentsCount":"6,620 students","lastUpdated":null,"targetAudiences":["Marketers , MBA students , Marketing students ,Entrepreneurs , Business leaders , Executive managers, Small business owners","Brand managers who want to enhance their work with strategy of storytelling","Graphic, motion designers \u0026 creative directors who want to explore the branding visualization storytelling","Advertisers who want to deliver their messages to the audience using brand story techniques","Ads and sales copywriters who want to influence their audiences with emotional and persuasive content"],"tags":["Business","Management","Storytelling"],"rating":{"count":21,"averageValue":"4.2"},"instructors":[{"name":"Musa Bin Adi","url":"/user/mha-92/","totalNumberOfStudents":9271,"totalNumberOfReviews":44,"averageRating":4.28191475}]},"isAlreadyAFreeCourse":false,"couponData":{"couponCode":"JUNE1207","originalPrice":"\u20B97,900","discountedPrice":"\u20B95,200","expirationText":"2 days","discountPercentage":34}},"https://www.udemy.com/course/power-bi-introduccion/":{"courseDetails":{"courseId":4445640,"title":"An\u00E1lisis de datos con Power BI","shortDescription":"Juan Carlos, con m\u00E1s de 10 a\u00F1os de experiencia en Business Intelligence, te ense\u00F1ar\u00E1 todo sobre Power BI","longDescription":null,"language":"Espa\u00F1ol","courseUri":"https://www.udemy.com/course/power-bi-introduccion/","imageUri":"https://img-c.udemycdn.com/course/750x422/4445640_58a5_3.jpg","duration":"4.5 total hours","enrolledStudentsCount":"12.375 estudiantes","lastUpdated":null,"targetAudiences":["Estudiantes y profesionales que quieran entrar en el mundo de los datos y el Business Intelligence.","Estudiantes y profesionales que quieran aprender a utilizar Power BI."],"tags":["Negocios","Anal\u00EDtica e inteligencia empresarial","Power BI de Microsoft"],"rating":{"count":163,"averageValue":"4.5"},"instructors":[{"name":"Numpi Cursos","url":"/user/numpi/","totalNumberOfStudents":350412,"totalNumberOfReviews":27810,"averageRating":4.38381375568727},{"name":"Juan Carlos Hernandez Ramirez","url":"/user/juan-carlos-hernandez-ramirez-4/","totalNumberOfStudents":21862,"totalNumberOfReviews":434,"averageRating":4.504591255882352}]},"isAlreadyAFreeCourse":false,"couponData":{"couponCode":"BESTPRICE_JUL2022_2","originalPrice":"3.399\u00A0INR","discountedPrice":"2.299\u00A0INR","expirationText":"2 d\u00EDas","discountPercentage":32}},"https://www.udemy.com/course/power-bi-analisis-avanzado-con-sql-y-programacion-en-r/":{"courseDetails":{"courseId":4555386,"title":"An\u00E1lisis avanzado con SQL y programaci\u00F3n en R con Power BI","shortDescription":"Juan Carlos, con m\u00E1s de 10 a\u00F1os de experiencia en Business Intelligence, te ense\u00F1ar\u00E1 funciones avanzadas en Power BI","longDescription":null,"language":"Spanish","courseUri":"https://www.udemy.com/course/power-bi-analisis-avanzado-con-sql-y-programacion-en-r/","imageUri":"https://img-c.udemycdn.com/course/750x422/4555386_6a2a_2.jpg","duration":"4 total hours","enrolledStudentsCount":"4,644 students","lastUpdated":null,"targetAudiences":["Estudiantes que quieran ir m\u00E1s all\u00E1 en el an\u00E1lisis de datos."],"tags":["Business","Business Analytics \u0026 Intelligence","Microsoft Power BI"],"rating":{"count":23,"averageValue":"4.5"},"instructors":[{"name":"Numpi Cursos","url":"/user/numpi/","totalNumberOfStudents":350412,"totalNumberOfReviews":27810,"averageRating":4.38381375568727},{"name":"Juan Carlos Hernandez Ramirez","url":"/user/juan-carlos-hernandez-ramirez-4/","totalNumberOfStudents":21862,"totalNumberOfReviews":434,"averageRating":4.504591255882352}]},"isAlreadyAFreeCourse":false,"couponData":{"couponCode":"BESTPRICE_JUL2022_2","originalPrice":"\u20B93,399","discountedPrice":"\u20B92,299","expirationText":"2 days","discountPercentage":32}},"https://www.udemy.com/course/how-to-build-neural-networks-in-python/":{"courseDetails":{"courseId":4731890,"title":"How to Build Neural Networks in Python","shortDescription":"The best course to learn to build and train a Deep Neural Network (DNN) using TensorFlow \u0026 Python in 90 minutes","longDescription":null,"language":"English","courseUri":"https://www.udemy.com/course/how-to-build-neural-networks-in-python/","imageUri":"https://img-c.udemycdn.com/course/750x422/4731890_e5c8_4.jpg","duration":"1.5 total hours","enrolledStudentsCount":"295 students","lastUpdated":null,"targetAudiences":["Whoever wants to learn to build neural network using Python"],"tags":["Development","Data Science","Neural Networks"],"rating":{"count":3,"averageValue":"5.0"},"instructors":[{"name":"Socrates Knowledge Academy","url":"/user/knowledge-socrates-academy/","totalNumberOfStudents":295,"totalNumberOfReviews":3,"averageRating":5},{"name":"Alessandro Piergentili","url":"/user/alessandro-piergentili-2/","totalNumberOfStudents":295,"totalNumberOfReviews":3,"averageRating":5},{"name":"Nuruzzaman Faruqui","url":"/user/nuruzzaman-faruqui/","totalNumberOfStudents":295,"totalNumberOfReviews":3,"averageRating":5}]},"isAlreadyAFreeCourse":false,"couponData":{"couponCode":"13F3F0DF982CBFA151AB","originalPrice":"\u20B9799","discountedPrice":"\u20B9549","expirationText":"2 days","discountPercentage":31}},"https://www.udemy.com/course/python-for-data-science-numpy-pandas-exercises/":{"courseDetails":{"courseId":4656122,"title":"230\u002B Exercises - Python for Data Science - NumPy \u002B Pandas","shortDescription":"Double pack! Improve your Python programming and data science skills and solve over 230 exercises in NumPy and Pandas!","longDescription":null,"language":"English","courseUri":"https://www.udemy.com/course/python-for-data-science-numpy-pandas-exercises/","imageUri":"https://img-b.udemycdn.com/course/750x422/4656122_aa2f.jpg","duration":"1 total hour","enrolledStudentsCount":"5,684 students","lastUpdated":null,"targetAudiences":["everyone who wants to learn by doing","everyone who wants to improve Python programming skills","everyone who wants to improve data science skills","everyone who wants to prepare for an interview"],"tags":["Development","Data Science"],"rating":{"count":9,"averageValue":"3.6"},"instructors":[{"name":"Pawe\u0142 Krakowiak","url":"/user/krakowiakpawel9/","totalNumberOfStudents":177567,"totalNumberOfReviews":4207,"averageRating":4.579001450841346}]},"isAlreadyAFreeCourse":false,"couponData":{"couponCode":"JULDROP2","originalPrice":"\u20B9799","discountedPrice":"\u20B9549","expirationText":"2 days","discountPercentage":31}},"https://www.udemy.com/course/b1-b2-seviyesinde-hikayeler-cevirerek-ingilizce-ogreniyoruz/":{"courseDetails":{"courseId":4668736,"title":"B1-B2 Seviyesinde Hikayeler \u00C7evirerek \u0130ngilizce \u00D6\u011Freniyoruz","shortDescription":"\u0130ngilizce B1 - B2, \u0130ngilizce Hikaye, \u0130ngilizce Haber, \u0130ngilizce \u00E7eviri, \u0130ngilizce okuma, \u0130ngilizce kursu, \u0130ngilizce","longDescription":null,"language":"T\u00FCrk\u00E7e","courseUri":"https://www.udemy.com/course/b1-b2-seviyesinde-hikayeler-cevirerek-ingilizce-ogreniyoruz/","imageUri":"https://img-c.udemycdn.com/course/750x422/4668736_b308.jpg","duration":"2.5 total hours","enrolledStudentsCount":"1.006 \u00F6\u011Frenci","lastUpdated":null,"targetAudiences":["\u0130ngilizce \u00F6\u011Frenmek isteyenler.","Kli\u015Fe y\u00F6ntemlerden s\u0131k\u0131l\u0131p daha e\u011Flenceli bir \u015Fekilde \u0130ngilizce \u00F6\u011Frenmenin yolunu arayanlar."],"tags":["\u00D6\u011Fretim ve Akademi","Dil \u00D6\u011Frenimi","\u0130ngilizce"],"rating":{"count":122,"averageValue":"5.0"},"instructors":[{"name":"Abdurrahman TEKIN","url":"/user/abdurrahman-tekin/","totalNumberOfStudents":19811,"totalNumberOfReviews":1098,"averageRating":4.719062261916462}]},"isAlreadyAFreeCourse":false,"couponData":{"couponCode":"850B7D960C3149F59B8E","originalPrice":"799\u00A0\u20B9","discountedPrice":"549\u00A0\u20B9","expirationText":"2 g\u00FCn","discountPercentage":31}},"https://www.udemy.com/course/how-to-edit-video-fast-adobe-premier-pro-step-by-step/":{"courseDetails":{"courseId":4733356,"title":"Learn to Edit Video FAST! Adobe Premiere Pro 2022 StepByStep","shortDescription":"Learn to Edit Quickly, Everything You Need with the New Adobe Premiere Pro 2022 Version, Start to Finish Full Course","longDescription":null,"language":"English","courseUri":"https://www.udemy.com/course/how-to-edit-video-fast-adobe-premier-pro-step-by-step/","imageUri":"https://img-b.udemycdn.com/course/750x422/4733356_b87c_2.jpg","duration":"5 total hours","enrolledStudentsCount":"1,171 students","lastUpdated":null,"targetAudiences":["Beginner Adobe Premier Pro Editors","Those with no editing experience","Intermediate video editors","Refresher course for Adobe Premier Pro (new 2022 version)"],"tags":["Photography \u0026 Video","Video Design","Adobe Premiere"],"rating":{"count":25,"averageValue":"4.8"},"instructors":[{"name":"Dan Britain","url":"/user/daniel-philpott-3/","totalNumberOfStudents":99644,"totalNumberOfReviews":1695,"averageRating":4.622295950898204}]},"isAlreadyAFreeCourse":false,"couponData":{"couponCode":"17167115C92E2E7F1474","originalPrice":"\u20B9799","discountedPrice":"\u20B9549","expirationText":"2 days","discountPercentage":31}},"https://www.udemy.com/course/python-3-crea-tu-primer-juego-con-pygame/":{"courseDetails":{"courseId":4555394,"title":"Crea tu primer juego con Pygame","shortDescription":"Ernesto, experto desarrollador Python, te guiar\u00E1 pasa a paso en la creaci\u00F3n de un videojuego desde cero.","longDescription":null,"language":"Spanish","courseUri":"https://www.udemy.com/course/python-3-crea-tu-primer-juego-con-pygame/","imageUri":"https://img-c.udemycdn.com/course/750x422/4555394_3b4e_3.jpg","duration":"7.5 total hours","enrolledStudentsCount":"9,539 students","lastUpdated":null,"targetAudiences":["Desarrolladores principiantes de Python interesados en videojuegos."],"tags":["Development","Programming Languages","Python Game Development"],"rating":{"count":38,"averageValue":"4.8"},"instructors":[{"name":"Numpi Cursos","url":"/user/numpi/","totalNumberOfStudents":350412,"totalNumberOfReviews":27810,"averageRating":4.38381375568727},{"name":"Ernesto Arreaga","url":"/user/ernesto-arreaga/","totalNumberOfStudents":9539,"totalNumberOfReviews":38,"averageRating":4.8403535}]},"isAlreadyAFreeCourse":false,"couponData":{"couponCode":"BESTPRICE_JUL2022_2","originalPrice":"\u20B9799","discountedPrice":"\u20B9549","expirationText":"2 days","discountPercentage":31}},"https://www.udemy.com/course/django-react-build-a-location-based-real-estate-website/":{"courseDetails":{"courseId":4628904,"title":"Django \u002B React : Build a Location-Based Real Estate Website","shortDescription":"In this course, Learn \u0026 practice React, Django, Django Rest Framework, GeoDjango, Material UI, React-Leaflet, PostGIS","longDescription":null,"language":"English","courseUri":"https://www.udemy.com/course/django-react-build-a-location-based-real-estate-website/","imageUri":"https://img-c.udemycdn.com/course/750x422/4628904_28d7_3.jpg","duration":"17 total hours","enrolledStudentsCount":"1,335 students","lastUpdated":null,"targetAudiences":["Developers who want take their skills to new levels.","Students who want to build real-world projects","Developers who want to play with maps","Map lovers"],"tags":["Development","Web Development","React"],"rating":{"count":31,"averageValue":"4.5"},"instructors":[{"name":"Abdel Diouf","url":"/user/abdel-diouf/","totalNumberOfStudents":1335,"totalNumberOfReviews":31,"averageRating":4.487872}]},"isAlreadyAFreeCourse":false,"couponData":{"couponCode":"67C9310A0DFF976F1C9E","originalPrice":"\u20B9799","discountedPrice":"\u20B9549","expirationText":"2 days","discountPercentage":31}},"https://www.udemy.com/course/google-professional-cloud-architect-data-engineer/":{"courseDetails":{"courseId":4773324,"title":"Google Professional Cloud Architect \u0026 Data Engineer Pack","shortDescription":"[2022] Prepare for the exam as Google Professional Cloud Architect or Google Professional Data Engineer!","longDescription":null,"language":"English","courseUri":"https://www.udemy.com/course/google-professional-cloud-architect-data-engineer/","imageUri":"https://img-b.udemycdn.com/course/750x422/4773324_24e2_2.jpg","duration":"465 questions","enrolledStudentsCount":"433 students","lastUpdated":null,"targetAudiences":["everyone who are about to take the Google Professional Cloud Architect exam","everyone who are about to take the Google Professional Data Engineer exam","everyone who wants to prepare for an interview with Google Cloud","everyone who wants to work with Google Cloud"],"tags":["IT \u0026 Software","IT Certifications"],"rating":null,"instructors":[{"name":"Pawe\u0142 Krakowiak","url":"/user/krakowiakpawel9/","totalNumberOfStudents":177567,"totalNumberOfReviews":4207,"averageRating":4.579001450841346}]},"isAlreadyAFreeCourse":false,"couponData":{"couponCode":"JULDROP","originalPrice":"\u20B9799","discountedPrice":"\u20B9549","expirationText":"2 days","discountPercentage":31}},"https://www.udemy.com/course/inculcating-positive-thinking-for-happiness-just-in-5-days/":{"courseDetails":{"courseId":4079942,"title":"Brain Computer Interfacing via spiking neuromorphic networks","shortDescription":"Spiking Neuromorphic Computing via PyCARL \u0026 Wyrm (Python): Understanding Brain Computer Interfacing (BCI) \u0026 Tiny ML","longDescription":null,"language":"English","courseUri":"https://www.udemy.com/course/inculcating-positive-thinking-for-happiness-just-in-5-days/","imageUri":"https://img-c.udemycdn.com/course/750x422/4079942_43d3_3.jpg","duration":"4 total hours","enrolledStudentsCount":"6,284 students","lastUpdated":null,"targetAudiences":["Beginners curious to learn about Brain Computer Interfacing using deep neural networks","Undergraduate \u0026 Graduate students aspire to kick start Human inspired Artificial Intelligence"],"tags":["Personal Development","Happiness","Positive Thinking"],"rating":{"count":37,"averageValue":"4.0"},"instructors":[{"name":"Junaid Zafar","url":"/user/junaid-zafar-10/","totalNumberOfStudents":49688,"totalNumberOfReviews":471,"averageRating":3.886079820689655}]},"isAlreadyAFreeCourse":false,"couponData":{"couponCode":"BCAB6153D0EB8653038D","originalPrice":"\u20B94,299","discountedPrice":"\u20B92,999","expirationText":"2 days","discountPercentage":30}},"https://www.udemy.com/course/fundamentos-de-programacion-r/":{"courseDetails":{"courseId":4586338,"title":"Fundamentos de Programaci\u00F3n: Aprende a programar desde cero","shortDescription":"De la teor\u00EDa a la pr\u00E1ctica","longDescription":null,"language":"Espa\u00F1ol","courseUri":"https://www.udemy.com/course/fundamentos-de-programacion-r/","imageUri":"https://img-c.udemycdn.com/course/750x422/4586338_dee3_2.jpg","duration":"3.5 total hours","enrolledStudentsCount":"7.336 estudiantes","lastUpdated":null,"targetAudiences":["El curso est\u00E1 dirigido a los estudiantes que quieran comenzar a trabajar en el mundo del desarrollo de software"],"tags":["Inform\u00E1tica y software","Inform\u00E1tica y software, otros","Programaci\u00F3n gen\u00E9rica"],"rating":{"count":68,"averageValue":"4.5"},"instructors":[{"name":"Numpi Cursos","url":"/user/numpi/","totalNumberOfStudents":350412,"totalNumberOfReviews":27810,"averageRating":4.38381375568727},{"name":"Hugo Aguilar Svonik","url":"/user/hugo-aguilar-svonik/","totalNumberOfStudents":37015,"totalNumberOfReviews":628,"averageRating":4.408043847058823}]},"isAlreadyAFreeCourse":false,"couponData":{"couponCode":"BESTPRICE_JUL2022_2","originalPrice":"3.699\u00A0INR","discountedPrice":"2.599\u00A0INR","expirationText":"2 d\u00EDas","discountPercentage":30}},"https://www.udemy.com/course/python-3-desde-cero-para-principiantes-y-no-programadores/":{"courseDetails":{"courseId":4515736,"title":"Python 3: Desde cero para principiantes y no programadores","shortDescription":"Uriel, con experiencia en empresas como Amazon y Didi, te ense\u00F1ar\u00E1 Python de una manera f\u00E1cil y sencilla.","longDescription":null,"language":"Spanish","courseUri":"https://www.udemy.com/course/python-3-desde-cero-para-principiantes-y-no-programadores/","imageUri":"https://img-c.udemycdn.com/course/750x422/4515736_065f_2.jpg","duration":"4 total hours","enrolledStudentsCount":"11,344 students","lastUpdated":null,"targetAudiences":["Estudiantes que quieran mejorar sus conocimientos de programaci\u00F3n.","Programadores que quieran aprender el lenguaje Python."],"tags":["Development","Programming Languages","Python"],"rating":{"count":112,"averageValue":"4.5"},"instructors":[{"name":"Numpi Cursos","url":"/user/numpi/","totalNumberOfStudents":350412,"totalNumberOfReviews":27810,"averageRating":4.38381375568727}]},"isAlreadyAFreeCourse":false,"couponData":{"couponCode":"BESTPRICE_JUL2022_2","originalPrice":"\u20B93,699","discountedPrice":"\u20B92,599","expirationText":"2 days","discountPercentage":30}},"https://www.udemy.com/course/learn-bootstrap-5-and-tailwind-from-scratch-with-project/":{"courseDetails":{"courseId":4668632,"title":"learn bootstrap 5 and tailwind from scratch with project","shortDescription":"in this courser you will learn how to work with bootstrap , tailwind CSS and some basic of java script","longDescription":null,"language":"English","courseUri":"https://www.udemy.com/course/learn-bootstrap-5-and-tailwind-from-scratch-with-project/","imageUri":"https://img-c.udemycdn.com/course/750x422/4668632_42ea_2.jpg","duration":"17.5 total hours","enrolledStudentsCount":"230 students","lastUpdated":null,"targetAudiences":["frontend developer","web developer","college student"],"tags":["Development","Web Development","Tailwind CSS"],"rating":null,"instructors":[{"name":"Creative Programmer","url":"/user/creative-programmer2/","totalNumberOfStudents":229,"totalNumberOfReviews":0,"averageRating":0}]},"isAlreadyAFreeCourse":false,"couponData":{"couponCode":"A87D86F34730C0B48DF9","originalPrice":"\u20B93,499","discountedPrice":"\u20B92,499","expirationText":"2 days","discountPercentage":29}},"https://www.udemy.com/course/ingilizceyi-guncel-haberler-cevirerek-ogreniyoruz/":{"courseDetails":{"courseId":4303905,"title":"\u0130ngilizce kursu:  BBC Haberleri \u00C7evirerek \u0130ngilizce \u00D6\u011Fren","shortDescription":"\u0130ngilizce okuma, \u0130ngilizce gramer, \u0130ngilizce anlama","longDescription":null,"language":"T\u00FCrk\u00E7e","courseUri":"https://www.udemy.com/course/ingilizceyi-guncel-haberler-cevirerek-ogreniyoruz/","imageUri":"https://img-c.udemycdn.com/course/750x422/4303905_f96b_2.jpg","duration":"7 total hours","enrolledStudentsCount":"1.122 \u00F6\u011Frenci","lastUpdated":null,"targetAudiences":["\u0130ngilizce \u00F6\u011Frenmek isteyen herkes.","Kli\u015Fe y\u00F6ntemlerden s\u0131k\u0131l\u0131p daha e\u011Flenceli bir \u015Fekilde \u0130ngilizce \u00F6\u011Frenmenin yolunu arayanlar.","\u0130ngilizce \u00F6\u011Frenirken bilgi de edinmek isteyenler."],"tags":["\u00D6\u011Fretim ve Akademi","Dil \u00D6\u011Frenimi","\u0130ngilizce"],"rating":{"count":147,"averageValue":"4.8"},"instructors":[{"name":"Abdurrahman TEKIN","url":"/user/abdurrahman-tekin/","totalNumberOfStudents":19811,"totalNumberOfReviews":1098,"averageRating":4.719062261916462}]},"isAlreadyAFreeCourse":false,"couponData":{"couponCode":"398AC6249577A90D80EC","originalPrice":"1.299\u00A0\u20B9","discountedPrice":"999\u00A0\u20B9","expirationText":"2 g\u00FCn","discountPercentage":23}},"https://www.udemy.com/course/easy-way-to-learn-python-for-beginners-2021/":{"courseDetails":{"courseId":3812128,"title":"Complete PYTHON Programming for Beginners - 2022","shortDescription":"The easiest way to learn Python in-depth and build complex, scalable programs!","longDescription":null,"language":"English","courseUri":"https://www.udemy.com/course/easy-way-to-learn-python-for-beginners-2021/","imageUri":"https://img-c.udemycdn.com/course/750x422/3812128_3674.jpg","duration":"11 total hours","enrolledStudentsCount":"131,406 students","lastUpdated":null,"targetAudiences":["Absolute Beginners","Non-Absolute Beginners","Intermediates"],"tags":["Development","Programming Languages","Python"],"rating":{"count":1699,"averageValue":"4.2"},"instructors":[{"name":"Hemanth kumar","url":"/user/hemanth-1546/","totalNumberOfStudents":454645,"totalNumberOfReviews":7222,"averageRating":4.330730472272728}]},"isAlreadyAFreeCourse":false,"couponData":{"couponCode":"14B225C5614C1BC99267","originalPrice":"\u20B91,299","discountedPrice":"\u20B9999","expirationText":"2 days","discountPercentage":23}},"https://www.udemy.com/course/bilgisayar-ogretmeninden-hzlandrlms-python3-kursu/":{"courseDetails":{"courseId":3899030,"title":"Bilgisayar \u00D6\u011Fretmeninden, Python Kursu","shortDescription":"S\u0131f\u0131rdan anlayarak Python \u00D6\u011Frenen !","longDescription":null,"language":"T\u00FCrk\u00E7e","courseUri":"https://www.udemy.com/course/bilgisayar-ogretmeninden-hzlandrlms-python3-kursu/","imageUri":"https://img-c.udemycdn.com/course/750x422/3899030_4165_3.jpg","duration":"10.5 total hours","enrolledStudentsCount":"7.744 \u00F6\u011Frenci","lastUpdated":null,"targetAudiences":["Python\u0027a Merak\u0131 Olan Her Ya\u015Ftan \u00D6\u011Frenciye Uygundur.","Lise ve \u00DCniversite \u00D6\u011Frencileri","Liselerde \u00C7al\u0131\u015Fan B\u00D6TE(Bili\u015Fim Teknolojileri) \u00F6\u011Fretmenleri"],"tags":["Yaz\u0131l\u0131m Geli\u015Ftirme","Programlama Dilleri","Python"],"rating":{"count":127,"averageValue":"4.8"},"instructors":[{"name":"Tuncay EROL","url":"/user/tuncay-erol/","totalNumberOfStudents":17741,"totalNumberOfReviews":832,"averageRating":4.82996107844523}]},"isAlreadyAFreeCourse":false,"couponData":{"couponCode":"04D31C0E725DECBF8172","originalPrice":"1.299\u00A0\u20B9","discountedPrice":"999\u00A0\u20B9","expirationText":"2 g\u00FCn","discountPercentage":23}}},"freeCourses":{"https://www.udemy.com/course/developing-app-using-flutter/":{"courseDetails":{"courseId":4609182,"title":"Developing app using Flutter","shortDescription":"Flutter, android app, Weather app, MySQL, Firebase, cloud firestore database, Rest APIs","longDescription":null,"language":"English","courseUri":"https://www.udemy.com/course/developing-app-using-flutter/","imageUri":"https://img-c.udemycdn.com/course/750x422/4609182_3653.jpg","duration":"1","enrolledStudentsCount":"5,774 students","lastUpdated":null,"targetAudiences":["Mobile App developer","Cross platform app developers"],"tags":["Development","Mobile Development","Google Flutter"],"rating":{"count":28,"averageValue":"4.5"},"instructors":[{"name":"Proton Expert Systems \u0026 Solutions","url":"/user/proton-expert-systems-solutions/","totalNumberOfStudents":25313,"totalNumberOfReviews":414,"averageRating":4.097697480454545}]},"isAlreadyAFreeCourse":true,"couponData":null},"https://www.udemy.com/course/net-zero/":{"courseDetails":{"courseId":4611422,"title":"Net Zero","shortDescription":"Get Your Business Ready For Future","longDescription":null,"language":"English","courseUri":"https://www.udemy.com/course/net-zero/","imageUri":"https://img-c.udemycdn.com/course/750x422/4611422_4ca9_2.jpg","duration":"1","enrolledStudentsCount":"640 students","lastUpdated":null,"targetAudiences":["Everybody who cares for the environment and the future of our planet"],"tags":["Business","Entrepreneurship","Environmental Management"],"rating":{"count":1,"averageValue":"5.0"},"instructors":[{"name":"Abdullah Ali-Ahmadi","url":"/user/abdullah-8434/","totalNumberOfStudents":1219,"totalNumberOfReviews":3,"averageRating":5}]},"isAlreadyAFreeCourse":true,"couponData":null},"https://www.udemy.com/course/blender-3d-create-a-cartoon-character/":{"courseDetails":{"courseId":3502990,"title":"Blender 3D - Create a Cartoon Character","shortDescription":"Create a cartoon character in Blender 3D from scratch. From zero to hero!","longDescription":null,"language":"English","courseUri":"https://www.udemy.com/course/blender-3d-create-a-cartoon-character/","imageUri":"https://img-c.udemycdn.com/course/750x422/3502990_c94e_2.jpg","duration":"1","enrolledStudentsCount":"1,880 students","lastUpdated":null,"targetAudiences":["Beginners in Blender that want to learn how to model basic characters"],"tags":["Design","3D \u0026 Animation","3D Modeling"],"rating":{"count":12,"averageValue":"4.3"},"instructors":[{"name":"Ivan Yosifov","url":"/user/martin-grigorov/","totalNumberOfStudents":13754,"totalNumberOfReviews":307,"averageRating":4.190137066666667}]},"isAlreadyAFreeCourse":true,"couponData":null},"https://www.udemy.com/course/wordpress-somali/":{"courseDetails":{"courseId":1548474,"title":"Sidee Loo Dhisaa Website Ganacsi Adoo Isticmaalaya Wordpress","shortDescription":"Baro sida loo abuuro website ganacsi oo WordPress ah iyadoo la isticmaalayo Elementor \u002B Astra Theme","longDescription":null,"language":"Somali","courseUri":"https://www.udemy.com/course/wordpress-somali/","imageUri":"https://img-c.udemycdn.com/course/750x422/1548474_2dae_2.jpg","duration":"6","enrolledStudentsCount":"1,038 students","lastUpdated":null,"targetAudiences":["Qof kasta oo xiiseynaya inuu barto sida loo dhiso website-ka","Qof kasta oo raba inuu barto sida loo isticmaalo Wordpress"],"tags":["Development","Web Development","WordPress"],"rating":{"count":62,"averageValue":"4.8"},"instructors":[{"name":"Abdirizak Hersi","url":"/user/abdirizak-hersi-2/","totalNumberOfStudents":14093,"totalNumberOfReviews":328,"averageRating":4.1139204125}]},"isAlreadyAFreeCourse":true,"couponData":null},"https://www.udemy.com/course/after-effects-tutorial-house-of-cards/":{"courseDetails":{"courseId":867136,"title":"After Effects: House of Cards Title Card Animation","shortDescription":"Learn how to re-create the animated House of Card title card in Adobe After Effects.","longDescription":null,"language":"English","courseUri":"https://www.udemy.com/course/after-effects-tutorial-house-of-cards/","imageUri":"https://img-c.udemycdn.com/course/750x422/867136_8d55_2.jpg","duration":"0","enrolledStudentsCount":"11,056 students","lastUpdated":null,"targetAudiences":["You should take this course if you are already familiar with After Effects and want to learn some new techniques with a fun project-based course.","You should also take this course if you are brand new to After Effects. If you are brand new, it might be more difficult to follow along."],"tags":["Design","3D \u0026 Animation","After Effects"],"rating":{"count":175,"averageValue":"4.4"},"instructors":[{"name":"Phil Ebiner","url":"/user/philipebiner2/","totalNumberOfStudents":2522609,"totalNumberOfReviews":340622,"averageRating":4.611234621602513},{"name":"Video School","url":"/user/phil-ebiner/","totalNumberOfStudents":2473814,"totalNumberOfReviews":359711,"averageRating":4.611234621602513}]},"isAlreadyAFreeCourse":true,"couponData":null}}}